Workbook

Sheet ESTRUTURA_ICOMON
A1: MATR_SAP | B1: RE_* | C1: NOME | D1: SUPERVISOR | E1: COORDENADOR
A2: 80585147 | B2: =IFERROR(A2*1,A2) -> 80585147 | C2: ADRIANO LUIZ DA ALMEIDA SALES | D2: DANILO LEANDRO AVALOS LOPES | E2: WELLINGTON DIAS DA COSTA
A3: 81011080 | B3: =IFERROR(A3*1,A3) -> 81011080 | C3: DAVID MADEIRA | D3: ALEX SILVA SOUSA | E3: DENIS DOS SANTOS
A4: 80165944 | B4: =IFERROR(A4*1,A4) -> 80165944 | C4: JEFFERSON DOS SANTOS PIO | D4: GABRIEL SILVA DIAS | E4: DENIS DOS SANTOS
A5: 80591964 | B5: =IFERROR(A5*1,A5) -> 80591964 | C5: SERGIO MARTINS HIAR JUNIOR | D5: IVAN FERNANDES BATISTA PINHEIRO | E5: WELLINGTON DIAS DA COSTA
A6: 80664035 | B6: =IFERROR(A6*1,A6) -> 80664035 | C6: CLAUDIANO ALVES TEIXEIRA | D6: JOSE ADRIANO LEITE DA SILVA | E6: WELLINGTON DIAS DA COSTA
A7: 80632754 | B7: =IFERROR(A7*1,A7) -> 80632754 | C7: JEFERSON GONCALVES FIGUEIREDO DE JESUS | D7: JOSE ADRIANO LEITE DA SILVA | E7: WELLINGTON DIAS DA COSTA
A8: 80194904 | B8: =IFERROR(A8*1,A8) -> 80194904 | C8: MAURO DOS SANTOS | D8: CLEBERSON MAGALHAES DE LIMA | E8: WELLINGTON DIAS DA COSTA
A9: 80184262 | B9: =IFERROR(A9*1,A9) -> 80184262 | C9: RUBEM MARQUES DA SILVA | D9: ALEXANDRE DE ALENCAR NOVAES | E9: DENIS DOS SANTOS
A10: 80828679 | B10: =IFERROR(A10*1,A10) -> 80828679 | C10: GILBERTO BANDEIRA DA SILVA | D10: FELIPE PEREIRA FEITOSA | E10: DERNIZAN SANTOS MARCIEIRA
A11: 81022579 | B11: =IFERROR(A11*1,A11) -> 81022579 | C11: MATHEUS FONTES SILVA | D11: FELIPE PEREIRA FEITOSA | E11: DERNIZAN SANTOS MARCIEIRA
A12: 80188726 | B12: =IFERROR(A12*1,A12) -> 80188726 | C12: RONILDO ALMEIDA DE SOUZA | D12: FELIPE PEREIRA FEITOSA | E12: DERNIZAN SANTOS MARCIEIRA
A13: 80521921 | B13: =IFERROR(A13*1,A13) -> 80521921 | C13: ANDERSON SOUZA DA SILVA | D13: ADRIANO MENDES DOS SANTOS | E13: DERNIZAN SANTOS MARCIEIRA
... A238: 80972529 | B238: =IFERROR(A238*1,A238) -> 80972529 | C238: VANDERLEI DIOGO DE OLIVEIRA | D238: DANILO LEANDRO AVALOS LOPES | E238: WELLINGTON DIAS DA COSTA

Sheet RIT_ICOMON
A1: ID | B1: DATA | C1: VISTORIADOR | D1: ANO | E1: MÊS | F1: SEMANA
A2: 42775 | B2: 46204 | C2: ANDRE MENDES DE SOUSA | D2: 2026 | E2: 7 | F2: 27
A3: 42772 | B3: 46204 | C3: MARCUS VINICIUS ARAUJO PRUDENTE | D3: 2026 | E3: 7 | F3: 27
A4: 42771 | B4: 46204 | C4: MARCUS VINICIUS ARAUJO PRUDENTE | D4: 2026 | E4: 7 | F4: 27
A5: 42770 | B5: 46204 | C5: AFONSO HENRIQUES MIGUEL MOREIRA | D5: 2026 | E5: 7 | F5: 27
A6: 42769 | B6: 46204 | C6: ARTHUR ROGERIO JERONIMO DA SILVA | D6: 2026 | E6: 7 | F6: 27
A7: 42768 | B7: 46204 | C7: ARTHUR ROGERIO JERONIMO DA SILVA | D7: 2026 | E7: 7 | F7: 27
A8: 42766 | B8: 46204 | C8: AFONSO HENRIQUES MIGUEL MOREIRA | D8: 2026 | E8: 7 | F8: 27
A9: 42765 | B9: 46204 | C9: AFONSO HENRIQUES MIGUEL MOREIRA | D9: 2026 | E9: 7 | F9: 27
A10: 42762 | B10: 46204 | C10: ALEX SILVA SOUSA | D10: 2026 | E10: 7 | F10: 27
A11: 42761 | B11: 46204 | C11: ALEX SILVA SOUSA | D11: 2026 | E11: 7 | F11: 27
A12: 42746 | B12: 46204 | C12: AFONSO HENRIQUES MIGUEL MOREIRA | D12: 2026 | E12: 7 | F12: 27
A13: 42745 | B13: 46204 | C13: DANILO LEANDRO AVALOS LOPES | D13: 2026 | E13: 7 | F13: 27
... A2306: 47867 | B2306: 46323 | C2306: DIEGO MENDONCA SANTOS | D2306: 2026 | E2306: 10 | F2306: 44

Sheet RIT_FUSIONS
A1: ID | B1: DATA | C1: VISTORIADOR | D1: FLAG_NOVO
A2: 47915 | B2: 46323 | C2: JOSE ADRIANO LEITE DA SILVA | D2: =IFERROR(VLOOKUP(RIT_FUSIONS[[#This Row],[ID]],RIT_ACUM!A:A,1,0),"NOVO") -> 47915
A3: 47914 | B3: 46323 | C3: JOSE ADRIANO LEITE DA SILVA | D3: =IFERROR(VLOOKUP(RIT_FUSIONS[[#This Row],[ID]],RIT_ACUM!A:A,1,0),"NOVO") -> 47914
A4: 47913 | B4: 46323 | C4: ADRIANO MENDES DOS SANTOS | D4: =IFERROR(VLOOKUP(RIT_FUSIONS[[#This Row],[ID]],RIT_ACUM!A:A,1,0),"NOVO") -> 47913
A5: 47912 | B5: 46323 | C5: ADRIANO MENDES DOS SANTOS | D5: =IFERROR(VLOOKUP(RIT_FUSIONS[[#This Row],[ID]],RIT_ACUM!A:A,1,0),"NOVO") -> 47912
A6: 47909 | B6: 46323 | C6: CLEBERSON MAGALHAES DE LIMA | D6: =IFERROR(VLOOKUP(RIT_FUSIONS[[#This Row],[ID]],RIT_ACUM!A:A,1,0),"NOVO") -> 47909
A7: 47908 | B7: 46323 | C7: ANDRE MENDES DE SOUSA | D7: =IFERROR(VLOOKUP(RIT_FUSIONS[[#This Row],[ID]],RIT_ACUM!A:A,1,0),"NOVO") -> 47908
A8: 47907 | B8: 46323 | C8: CLEBERSON MAGALHAES DE LIMA | D8: =IFERROR(VLOOKUP(RIT_FUSIONS[[#This Row],[ID]],RIT_ACUM!A:A,1,0),"NOVO") -> 47907
A9: 47906 | B9: 46323 | C9: CLEBERSON MAGALHAES DE LIMA | D9: =IFERROR(VLOOKUP(RIT_FUSIONS[[#This Row],[ID]],RIT_ACUM!A:A,1,0),"NOVO") -> 47906
A10: 47904 | B10: 46323 | C10: DIEGO MENDONCA SANTOS | D10: =IFERROR(VLOOKUP(RIT_FUSIONS[[#This Row],[ID]],RIT_ACUM!A:A,1,0),"NOVO") -> 47904
A11: 47902 | B11: 46323 | C11: MARCUS VINICIUS ARAUJO PRUDENTE | D11: =IFERROR(VLOOKUP(RIT_FUSIONS[[#This Row],[ID]],RIT_ACUM!A:A,1,0),"NOVO") -> 47902
A12: 47901 | B12: 46323 | C12: MARCUS VINICIUS ARAUJO PRUDENTE | D12: =IFERROR(VLOOKUP(RIT_FUSIONS[[#This Row],[ID]],RIT_ACUM!A:A,1,0),"NOVO") -> 47901
A13: 47900 | B13: 46323 | C13: MARCUS VINICIUS ARAUJO PRUDENTE | D13: =IFERROR(VLOOKUP(RIT_FUSIONS[[#This Row],[ID]],RIT_ACUM!A:A,1,0),"NOVO") -> 47900
... A831: 46381 | B831: 46284 | C831: JOSE ADRIANO LEITE DA SILVA | D831: =IFERROR(VLOOKUP(RIT_FUSIONS[[#This Row],[ID]],RIT_ACUM!A:A,1,0),"NOVO") -> 46381

Sheet RIT_ACUM
A1: ID | B1: DATA | C1: VISTORIADOR | D1: MÊS
A2: 42775 | B2: 46204 | C2: ANDRE MENDES DE SOUSA | D2: =MONTH(B2) -> 7
A3: 42772 | B3: 46204 | C3: MARCUS VINICIUS ARAUJO PRUDENTE | D3: =MONTH(B3) -> 7
A4: 42771 | B4: 46204 | C4: MARCUS VINICIUS ARAUJO PRUDENTE | D4: =MONTH(B4) -> 7
A5: 42770 | B5: 46204 | C5: AFONSO HENRIQUES MIGUEL MOREIRA | D5: =MONTH(B5) -> 7
A6: 42769 | B6: 46204 | C6: ARTHUR ROGERIO JERONIMO DA SILVA | D6: =MONTH(B6) -> 7
A7: 42768 | B7: 46204 | C7: ARTHUR ROGERIO JERONIMO DA SILVA | D7: =MONTH(B7) -> 7
A8: 42766 | B8: 46204 | C8: AFONSO HENRIQUES MIGUEL MOREIRA | D8: =MONTH(B8) -> 7
A9: 42765 | B9: 46204 | C9: AFONSO HENRIQUES MIGUEL MOREIRA | D9: =MONTH(B9) -> 7
A10: 42762 | B10: 46204 | C10: ALEX SILVA SOUSA | D10: =MONTH(B10) -> 7
A11: 42761 | B11: 46204 | C11: ALEX SILVA SOUSA | D11: =MONTH(B11) -> 7
A12: 42746 | B12: 46204 | C12: AFONSO HENRIQUES MIGUEL MOREIRA | D12: =MONTH(B12) -> 7
A13: 42745 | B13: 46204 | C13: DANILO LEANDRO AVALOS LOPES | D13: =MONTH(B13) -> 7
... A2306: 47826 | B2306: 46322 | C2306: DIEGO MENDONCA SANTOS | D2306: =MONTH(B2306) -> 10

Sheet CHECK_FUSIONS
A1: ID | B1: DATA | C1: VISTORIADOR | D1: FLAG_NOVO
A2: 7669 | B2: 46323.753 | C2: AFONSO HENRIQUES MIGUEL MOREIRA | D2: =IFERROR(VLOOKUP(_2__Ferramental_AST[[#This Row],[ID]],CHECK_ACUM!A:A,1,0),"NOVO") -> 7669
A3: 7668 | B3: 46323.753 | C3: AFONSO HENRIQUES MIGUEL MOREIRA | D3: =IFERROR(VLOOKUP(_2__Ferramental_AST[[#This Row],[ID]],CHECK_ACUM!A:A,1,0),"NOVO") -> 7668
A4: 7667 | B4: 46323.751 | C4: AFONSO HENRIQUES MIGUEL MOREIRA | D4: =IFERROR(VLOOKUP(_2__Ferramental_AST[[#This Row],[ID]],CHECK_ACUM!A:A,1,0),"NOVO") -> 7667
A5: 7666 | B5: 46323.75 | C5: AFONSO HENRIQUES MIGUEL MOREIRA | D5: =IFERROR(VLOOKUP(_2__Ferramental_AST[[#This Row],[ID]],CHECK_ACUM!A:A,1,0),"NOVO") -> 7666
A6: 7665 | B6: 46323.749 | C6: AFONSO HENRIQUES MIGUEL MOREIRA | D6: =IFERROR(VLOOKUP(_2__Ferramental_AST[[#This Row],[ID]],CHECK_ACUM!A:A,1,0),"NOVO") -> 7665
A7: 7664 | B7: 46323.697 | C7: DIEGO MENDONCA SANTOS | D7: =IFERROR(VLOOKUP(_2__Ferramental_AST[[#This Row],[ID]],CHECK_ACUM!A:A,1,0),"NOVO") -> 7664
A8: 7663 | B8: 46323.618 | C8: DEYVISON BRUNO CUTRIM FERREIRA | D8: =IFERROR(VLOOKUP(_2__Ferramental_AST[[#This Row],[ID]],CHECK_ACUM!A:A,1,0),"NOVO") -> 7663
A9: 7662 | B9: 46323.616 | C9: DEYVISON BRUNO CUTRIM FERREIRA | D9: =IFERROR(VLOOKUP(_2__Ferramental_AST[[#This Row],[ID]],CHECK_ACUM!A:A,1,0),"NOVO") -> 7662
A10: 7661 | B10: 46322.408 | C10: ALEXANDRE MORAIS MEDEIROS DA SILVA | D10: =IFERROR(VLOOKUP(_2__Ferramental_AST[[#This Row],[ID]],CHECK_ACUM!A:A,1,0),"NOVO") -> 7661
A11: 7660 | B11: 46323.399 | C11: DEYVISON BRUNO CUTRIM FERREIRA | D11: =IFERROR(VLOOKUP(_2__Ferramental_AST[[#This Row],[ID]],CHECK_ACUM!A:A,1,0),"NOVO") -> 7660
A12: 7659 | B12: 46323.398 | C12: DEYVISON BRUNO CUTRIM FERREIRA | D12: =IFERROR(VLOOKUP(_2__Ferramental_AST[[#This Row],[ID]],CHECK_ACUM!A:A,1,0),"NOVO") -> 7659
A13: 7658 | B13: 46322.751 | C13: AFONSO HENRIQUES MIGUEL MOREIRA | D13: =IFERROR(VLOOKUP(_2__Ferramental_AST[[#This Row],[ID]],CHECK_ACUM!A:A,1,0),"NOVO") -> 7658
... A204: 7437 | B204: 46286.661 | C204: ANDRE MENDES DE SOUSA | D204: =IFERROR(VLOOKUP(_2__Ferramental_AST[[#This Row],[ID]],CHECK_ACUM!A:A,1,0),"NOVO") -> 7437

Sheet CHECK_ACUM
A1: ID | B1: DATA | C1: VISTORIADOR | D1: MÊS
A2: 6173 | B2: 46147 | C2: EMERSON PINTO BISPO | D2: =MONTH(B2) -> 5
A3: 6170 | B3: 46147 | C3: NILTON CAMPOS DE BARROS | D3: =MONTH(B3) -> 5
A4: 6183 | B4: 46148 | C4: AFONSO HENRIQUES MIGUEL MOREIRA | D4: =MONTH(B4) -> 5
A5: 6182 | B5: 46148 | C5: DENIS REIS | D5: =MONTH(B5) -> 5
A6: 6181 | B6: 46148 | C6: DEYVISON BRUNO CUTRIM FERREIRA | D6: =MONTH(B6) -> 5
A7: 6180 | B7: 46148 | C7: DEYVISON BRUNO CUTRIM FERREIRA | D7: =MONTH(B7) -> 5
A8: 6177 | B8: 46148 | C8: PRISCILA DE MELO SEVILHA ZANDELI | D8: =MONTH(B8) -> 5
A9: 6176 | B9: 46148 | C9: NILTON CAMPOS DE BARROS | D9: =MONTH(B9) -> 5
A10: 6206 | B10: 46149 | C10: CARMINE AVARESE FILHO | D10: =MONTH(B10) -> 5
A11: 6205 | B11: 46149 | C11: CARMINE AVARESE FILHO | D11: =MONTH(B11) -> 5
A12: 6204 | B12: 46149 | C12: CARMINE AVARESE FILHO | D12: =MONTH(B12) -> 5
A13: 6203 | B13: 46149 | C13: DENIS REIS | D13: =MONTH(B13) -> 5
... A872: 7651 | B872: 46322.412 | C872: DEYVISON BRUNO CUTRIM FERREIRA | D872: =MONTH(B872) -> 10

Sheet DEG_REDE
A1: ID | B1: DATA | C1: GESTORES | D1: FLAG_NOVO
A2: 204 | B2: 46150 | C2: Carmine Avarese Filho | D2: =IFERROR(VLOOKUP(DEG_REDE[[#This Row],[ID]],DEG_ACUM!A:A,1,0),"NOVO") -> 204
A3: 205 | B3: 46150 | C3: Carmine Avarese Filho | D3: =IFERROR(VLOOKUP(DEG_REDE[[#This Row],[ID]],DEG_ACUM!A:A,1,0),"NOVO") -> 205
A4: 206 | B4: 46150 | C4: Carmine Avarese Filho | D4: =IFERROR(VLOOKUP(DEG_REDE[[#This Row],[ID]],DEG_ACUM!A:A,1,0),"NOVO") -> 206
A5: 207 | B5: 46150 | C5: Carmine Avarese Filho | D5: =IFERROR(VLOOKUP(DEG_REDE[[#This Row],[ID]],DEG_ACUM!A:A,1,0),"NOVO") -> 207
A6: 208 | B6: 46150 | C6: Carmine Avarese Filho | D6: =IFERROR(VLOOKUP(DEG_REDE[[#This Row],[ID]],DEG_ACUM!A:A,1,0),"NOVO") -> 208
A7: 209 | B7: 46150 | C7: Carmine Avarese Filho | D7: =IFERROR(VLOOKUP(DEG_REDE[[#This Row],[ID]],DEG_ACUM!A:A,1,0),"NOVO") -> 209
A8: 210 | B8: 46150 | C8: Carmine Avarese Filho | D8: =IFERROR(VLOOKUP(DEG_REDE[[#This Row],[ID]],DEG_ACUM!A:A,1,0),"NOVO") -> 210
A9: 211 | B9: 46150 | C9: Carmine Avarese Filho | D9: =IFERROR(VLOOKUP(DEG_REDE[[#This Row],[ID]],DEG_ACUM!A:A,1,0),"NOVO") -> 211
A10: 212 | B10: 46150 | C10: Carmine Avarese Filho | D10: =IFERROR(VLOOKUP(DEG_REDE[[#This Row],[ID]],DEG_ACUM!A:A,1,0),"NOVO") -> 212
A11: 213 | B11: 46150 | C11: Carmine Avarese Filho | D11: =IFERROR(VLOOKUP(DEG_REDE[[#This Row],[ID]],DEG_ACUM!A:A,1,0),"NOVO") -> 213
A12: 214 | B12: 46150 | C12: Carmine Avarese Filho | D12: =IFERROR(VLOOKUP(DEG_REDE[[#This Row],[ID]],DEG_ACUM!A:A,1,0),"NOVO") -> 214
A13: 215 | B13: 46150 | C13: Carmine Avarese Filho | D13: =IFERROR(VLOOKUP(DEG_REDE[[#This Row],[ID]],DEG_ACUM!A:A,1,0),"NOVO") -> 215
... A1369: 3645 | B1369: 46324 | C1369: Andre Mendes De Sousa | D1369: =IFERROR(VLOOKUP(DEG_REDE[[#This Row],[ID]],DEG_ACUM!A:A,1,0),"NOVO") -> 3645

Sheet DEG_ACUM
A1: ID | B1: DATA | C1: VISTORIADOR | D1: MÊS
A2: 25856 | B2: 46024 | C2: MARCIA DOS SANTOS MATSUDA | D2: =MONTH(Tabela6[[#This Row],[DATA]]) -> 1
A3: 25857 | B3: 46024 | C3: MARCIA DOS SANTOS MATSUDA | D3: =MONTH(Tabela6[[#This Row],[DATA]]) -> 1
A4: 25858 | B4: 46024 | C4: MARCIA DOS SANTOS MATSUDA | D4: =MONTH(Tabela6[[#This Row],[DATA]]) -> 1
A5: 25859 | B5: 46024 | C5: MARCIA DOS SANTOS MATSUDA | D5: =MONTH(Tabela6[[#This Row],[DATA]]) -> 1
A6: 25861 | B6: 46027 | C6: DEYVISON BRUNO CUTRIM FERREIRA | D6: =MONTH(Tabela6[[#This Row],[DATA]]) -> 1
A7: 25862 | B7: 46027 | C7: DEYVISON BRUNO CUTRIM FERREIRA | D7: =MONTH(Tabela6[[#This Row],[DATA]]) -> 1
A8: 25863 | B8: 46027 | C8: DEYVISON BRUNO CUTRIM FERREIRA | D8: =MONTH(Tabela6[[#This Row],[DATA]]) -> 1
A9: 25864 | B9: 46027 | C9: DEYVISON BRUNO CUTRIM FERREIRA | D9: =MONTH(Tabela6[[#This Row],[DATA]]) -> 1
A10: 25865 | B10: 46027 | C10: DEYVISON BRUNO CUTRIM FERREIRA | D10: =MONTH(Tabela6[[#This Row],[DATA]]) -> 1
A11: 25866 | B11: 46027 | C11: DEYVISON BRUNO CUTRIM FERREIRA | D11: =MONTH(Tabela6[[#This Row],[DATA]]) -> 1
A12: 25867 | B12: 46027 | C12: EMERSON PINTO BISPO | D12: =MONTH(Tabela6[[#This Row],[DATA]]) -> 1
A13: 25868 | B13: 46027 | C13: EMERSON PINTO BISPO | D13: =MONTH(Tabela6[[#This Row],[DATA]]) -> 1
... A2483: 3645 | B2483: 46324 | C2483: Andre Mendes De Sousa | D2483: =MONTH(Tabela6[[#This Row],[DATA]]) -> 10

Sheet CLEAN-UP_ACUM
A1: ID | B1: DATA | C1: VISTORIADOR | D1: MÊS
A2: 30 | B2: 46028 | C2: DENIS REIS | D2: =MONTH(Tabela9[[#This Row],[DATA]]) -> 1
A3: 30 | B3: 46028 | C3: DENIS REIS | D3: =MONTH(Tabela9[[#This Row],[DATA]]) -> 1
A4: 31 | B4: 46036 | C4: BRUNO ARAUJO DE OLIVEIRA COELHO | D4: =MONTH(Tabela9[[#This Row],[DATA]]) -> 1
A5: 31 | B5: 46036 | C5: BRUNO ARAUJO DE OLIVEIRA COELHO | D5: =MONTH(Tabela9[[#This Row],[DATA]]) -> 1
A6: 32 | B6: 46042 | C6: BRUNO ARAUJO DE OLIVEIRA COELHO | D6: =MONTH(Tabela9[[#This Row],[DATA]]) -> 1
A7: 32 | B7: 46042 | C7: BRUNO ARAUJO DE OLIVEIRA COELHO | D7: =MONTH(Tabela9[[#This Row],[DATA]]) -> 1
A8: 33 | B8: 46055 | C8: BRUNO ARAUJO DE OLIVEIRA COELHO | D8: =MONTH(Tabela9[[#This Row],[DATA]]) -> 2
A9: 33 | B9: 46055 | C9: BRUNO ARAUJO DE OLIVEIRA COELHO | D9: =MONTH(Tabela9[[#This Row],[DATA]]) -> 2
A10: 34 | B10: 46057 | C10: AFONSO HENRIQUES MIGUEL MOREIRA | D10: =MONTH(Tabela9[[#This Row],[DATA]]) -> 2
A11: 34 | B11: 46057 | C11: AFONSO HENRIQUES MIGUEL MOREIRA | D11: =MONTH(Tabela9[[#This Row],[DATA]]) -> 2
A12: 35 | B12: 46065 | C12: BRUNO ARAUJO DE OLIVEIRA COELHO | D12: =MONTH(Tabela9[[#This Row],[DATA]]) -> 2
A13: 35 | B13: 46065 | C13: BRUNO ARAUJO DE OLIVEIRA COELHO | D13: =MONTH(Tabela9[[#This Row],[DATA]]) -> 2
... A242: 164 | B242: 46323 | C242: ALEXANDRE MORAIS MEDEIROS DA SILVA | D242: =MONTH(Tabela9[[#This Row],[DATA]]) -> 10

Sheet FISCALIZAÇÃO
A1: ID | B1: DATA | C1: GESTORES | D1: FLAG_NOVO
A2: 1474 | B2: 46077 | C2: CLEITON TRINDADE | D2: =IFERROR(VLOOKUP(FISCALIZAÇÃO[[#This Row],[ID]],FISC_ACUM!A:A,1,0),"NOVO") -> 1474
A3: 1480 | B3: 46078 | C3: CLEITON TRINDADE | D3: =IFERROR(VLOOKUP(FISCALIZAÇÃO[[#This Row],[ID]],FISC_ACUM!A:A,1,0),"NOVO") -> 1480
A4: 1490 | B4: 46078 | C4: DENIS REIS | D4: =IFERROR(VLOOKUP(FISCALIZAÇÃO[[#This Row],[ID]],FISC_ACUM!A:A,1,0),"NOVO") -> 1490
A5: 1491 | B5: 46078 | C5: DEYVISON BRUNO CUTRIM FERREIRA | D5: =IFERROR(VLOOKUP(FISCALIZAÇÃO[[#This Row],[ID]],FISC_ACUM!A:A,1,0),"NOVO") -> 1491
A6: 1487 | B6: 46078 | C6: DENIS REIS | D6: =IFERROR(VLOOKUP(FISCALIZAÇÃO[[#This Row],[ID]],FISC_ACUM!A:A,1,0),"NOVO") -> 1487
A7: 1488 | B7: 46078 | C7: BRUNO ARAUJO DE OLIVEIRA COELHO | D7: =IFERROR(VLOOKUP(FISCALIZAÇÃO[[#This Row],[ID]],FISC_ACUM!A:A,1,0),"NOVO") -> 1488
A8: 1502 | B8: 46078 | C8: BRUNO ARAUJO DE OLIVEIRA COELHO | D8: =IFERROR(VLOOKUP(FISCALIZAÇÃO[[#This Row],[ID]],FISC_ACUM!A:A,1,0),"NOVO") -> 1502
A9: 1503 | B9: 46078 | C9: BRUNO ARAUJO DE OLIVEIRA COELHO | D9: =IFERROR(VLOOKUP(FISCALIZAÇÃO[[#This Row],[ID]],FISC_ACUM!A:A,1,0),"NOVO") -> 1503
A10: 1504 | B10: 46078 | C10: DEYVISON BRUNO CUTRIM FERREIRA | D10: =IFERROR(VLOOKUP(FISCALIZAÇÃO[[#This Row],[ID]],FISC_ACUM!A:A,1,0),"NOVO") -> 1504
A11: 1505 | B11: 46078 | C11: DEYVISON BRUNO CUTRIM FERREIRA | D11: =IFERROR(VLOOKUP(FISCALIZAÇÃO[[#This Row],[ID]],FISC_ACUM!A:A,1,0),"NOVO") -> 1505
A12: 1506 | B12: 46078 | C12: DEYVISON BRUNO CUTRIM FERREIRA | D12: =IFERROR(VLOOKUP(FISCALIZAÇÃO[[#This Row],[ID]],FISC_ACUM!A:A,1,0),"NOVO") -> 1506
A13: 1511 | B13: 46079 | C13: NILTON CAMPOS DE BARROS | D13: =IFERROR(VLOOKUP(FISCALIZAÇÃO[[#This Row],[ID]],FISC_ACUM!A:A,1,0),"NOVO") -> 1511
... A644: 2659 | B644: 46315 | C644: DIEGO MENDONCA SANTOS | D644: =IFERROR(VLOOKUP(FISCALIZAÇÃO[[#This Row],[ID]],FISC_ACUM!A:A,1,0),"NOVO") -> 2659

Sheet FISC_ACUM
A1: ID | B1: DATA | C1: VISTORIADOR | D1: MÊS
A2: 1474 | B2: 46077 | C2: CLEITON TRINDADE | D2: =MONTH(Tabela12[[#This Row],[DATA]]) -> 2
A3: 1480 | B3: 46078 | C3: CLEITON TRINDADE | D3: =MONTH(Tabela12[[#This Row],[DATA]]) -> 2
A4: 1490 | B4: 46078 | C4: DENIS REIS | D4: =MONTH(Tabela12[[#This Row],[DATA]]) -> 2
A5: 1491 | B5: 46078 | C5: DEYVISON BRUNO CUTRIM FERREIRA | D5: =MONTH(Tabela12[[#This Row],[DATA]]) -> 2
A6: 1487 | B6: 46078 | C6: DENIS REIS | D6: =MONTH(Tabela12[[#This Row],[DATA]]) -> 2
A7: 1488 | B7: 46078 | C7: BRUNO ARAUJO DE OLIVEIRA COELHO | D7: =MONTH(Tabela12[[#This Row],[DATA]]) -> 2
A8: 1502 | B8: 46078 | C8: BRUNO ARAUJO DE OLIVEIRA COELHO | D8: =MONTH(Tabela12[[#This Row],[DATA]]) -> 2
A9: 1503 | B9: 46078 | C9: BRUNO ARAUJO DE OLIVEIRA COELHO | D9: =MONTH(Tabela12[[#This Row],[DATA]]) -> 2
A10: 1504 | B10: 46078 | C10: DEYVISON BRUNO CUTRIM FERREIRA | D10: =MONTH(Tabela12[[#This Row],[DATA]]) -> 2
A11: 1505 | B11: 46078 | C11: DEYVISON BRUNO CUTRIM FERREIRA | D11: =MONTH(Tabela12[[#This Row],[DATA]]) -> 2
A12: 1506 | B12: 46078 | C12: DEYVISON BRUNO CUTRIM FERREIRA | D12: =MONTH(Tabela12[[#This Row],[DATA]]) -> 2
A13: 1511 | B13: 46079 | C13: NILTON CAMPOS DE BARROS | D13: =MONTH(Tabela12[[#This Row],[DATA]]) -> 2
... A644: 2659 | B644: 46315 | C644: DIEGO MENDONCA SANTOS | D644: =MONTH(Tabela12[[#This Row],[DATA]]) -> 10

Sheet SD_7
A1: DATA | B1: GESTORES
A2: 45721 | B2: CLEYTON RODRIGUES
A3: 45729 | B3: ROBERTO DO NASCIMENTO GRAMA
A4: 45734 | B4: CLEYTON RODRIGUES
A5: 45734 | B5: CLEYTON RODRIGUES
A6: 45734 | B6: CLEYTON RODRIGUES
A7: 45734 | B7: CLEYTON RODRIGUES
A8: 45734 | B8: CLEYTON RODRIGUES
A9: 45734 | B9: KAIQUE MARCHIORI
A10: 45734 | B10: MARCIO FREIRE
A11: 45734 | B11: MARCIO FREIRE
A12: 45735 | B12: CLEYTON RODRIGUES
A13: 45735 | B13: CLEYTON RODRIGUES
... A3421: 46323 | B3421: DEYVISON BRUNO CUTRIM FERREIRA

Sheet SD_ACUM
A1: DATA | B1: VISTORIADOR | C1: ANO | D1: MÊS
A2: 46028 | B2: DEYVISON BRUNO CUTRIM FERREIRA | C2: =YEAR(Tabela14[[#This Row],[DATA]]) -> 2026 | D2: =MONTH(Tabela14[[#This Row],[DATA]]) -> 1
A3: 46028 | B3: DEYVISON BRUNO CUTRIM FERREIRA | C3: =YEAR(Tabela14[[#This Row],[DATA]]) -> 2026 | D3: =MONTH(Tabela14[[#This Row],[DATA]]) -> 1
A4: 46035 | B4: DEYVISON BRUNO CUTRIM FERREIRA | C4: =YEAR(Tabela14[[#This Row],[DATA]]) -> 2026 | D4: =MONTH(Tabela14[[#This Row],[DATA]]) -> 1
A5: 46035 | B5: NILTON CAMPOS DE BARROS | C5: =YEAR(Tabela14[[#This Row],[DATA]]) -> 2026 | D5: =MONTH(Tabela14[[#This Row],[DATA]]) -> 1
A6: 46055 | B6: AFONSO HENRIQUES MIGUEL MOREIRA | C6: =YEAR(Tabela14[[#This Row],[DATA]]) -> 2026 | D6: =MONTH(Tabela14[[#This Row],[DATA]]) -> 2
A7: 46055 | B7: AFONSO HENRIQUES MIGUEL MOREIRA | C7: =YEAR(Tabela14[[#This Row],[DATA]]) -> 2026 | D7: =MONTH(Tabela14[[#This Row],[DATA]]) -> 2
A8: 46055 | B8: AFONSO HENRIQUES MIGUEL MOREIRA | C8: =YEAR(Tabela14[[#This Row],[DATA]]) -> 2026 | D8: =MONTH(Tabela14[[#This Row],[DATA]]) -> 2
A9: 46055 | B9: AFONSO HENRIQUES MIGUEL MOREIRA | C9: =YEAR(Tabela14[[#This Row],[DATA]]) -> 2026 | D9: =MONTH(Tabela14[[#This Row],[DATA]]) -> 2
A10: 46055 | B10: AFONSO HENRIQUES MIGUEL MOREIRA | C10: =YEAR(Tabela14[[#This Row],[DATA]]) -> 2026 | D10: =MONTH(Tabela14[[#This Row],[DATA]]) -> 2
A11: 46055 | B11: EMERSON PINTO BISPO | C11: =YEAR(Tabela14[[#This Row],[DATA]]) -> 2026 | D11: =MONTH(Tabela14[[#This Row],[DATA]]) -> 2
A12: 46055 | B12: EMERSON PINTO BISPO | C12: =YEAR(Tabela14[[#This Row],[DATA]]) -> 2026 | D12: =MONTH(Tabela14[[#This Row],[DATA]]) -> 2
A13: 46055 | B13: BRUNO ARAUJO DE OLIVEIRA COELHO | C13: =YEAR(Tabela14[[#This Row],[DATA]]) -> 2026 | D13: =MONTH(Tabela14[[#This Row],[DATA]]) -> 2
... A1476: 46323 | B1476: DEYVISON BRUNO CUTRIM FERREIRA | C1476: =YEAR(Tabela14[[#This Row],[DATA]]) -> 2026 | D1476: =MONTH(Tabela14[[#This Row],[DATA]]) -> 10

Sheet FMO
A1: DATA ENVIO | B1: GESTORES
A2: 45708 | B2: JULIANA YONE DE SOUZA PEREIRA
A3: 45708 | B3: JULIANA YONE DE SOUZA PEREIRA
A4: 45708 | B4: JULIANA YONE DE SOUZA PEREIRA
A5: 45708 | B5: JULIANA YONE DE SOUZA PEREIRA
A6: 46027 | B6: DEYVISON BRUNO CUTRIM FERREIRA
A7: 46030 | B7: THAYNA ELIZABETE GOMES DA SILVA
A8: 46030 | B8: THEOGENES PAULO SESTREM PALOPOLI
A9: 46030 | B9: THEOGENES PAULO SESTREM PALOPOLI
A10: 46030 | B10: RENATA SILVA DE SOUSA
A11: 46030 | B11: THAYNA ELIZABETE GOMES DA SILVA
A12: 46031 | B12: THAYNA ELIZABETE GOMES DA SILVA
A13: 46031 | B13: THEOGENES PAULO SESTREM PALOPOLI
... A526: 46273 | B526: CARMINE AVARESE FILHO
A527: 46273
A528: 46273 | B528: CARMINE AVARESE FILHO
A529: 46273 | B529: CARMINE AVARESE FILHO
A530: 46273 | B530: CARMINE AVARESE FILHO
A531: 46275 | B531: CARMINE AVARESE FILHO
A532: 46275 | B532: ARTHUR GOMES
A533: 46275 | B533: ANDRE MENDES DE SOUSA
A534: 46276 | B534: ALEXANDRE MORAIS MEDEIROS
A535: 46276 | B535: CARMINE AVARESE FILHO
A536: 46276 | B536: CARMINE AVARESE FILHO
A537: 46276 | B537: DEYVISON BRUNO CUTRIM FERREIRA
A538: 46276 | B538: ARTHUR GOMES
A539: 46276 | B539: DEYVISON BRUNO CUTRIM FERREIRA
... A674: 46323 | B674: ARTHUR GOMES

Sheet FMO_ACUM
A1: DATA | B1: VISTORIADOR | C1: MÊS
A2: 45708 | B2: JULIANA YONE DE SOUZA PEREIRA | C2: =MONTH(Tabela16[[#This Row],[DATA]]) -> 2
A3: 45708 | B3: JULIANA YONE DE SOUZA PEREIRA | C3: =MONTH(Tabela16[[#This Row],[DATA]]) -> 2
A4: 45708 | B4: JULIANA YONE DE SOUZA PEREIRA | C4: =MONTH(Tabela16[[#This Row],[DATA]]) -> 2
A5: 45708 | B5: JULIANA YONE DE SOUZA PEREIRA | C5: =MONTH(Tabela16[[#This Row],[DATA]]) -> 2
A6: 46027 | B6: DEYVISON BRUNO CUTRIM FERREIRA | C6: =MONTH(Tabela16[[#This Row],[DATA]]) -> 1
A7: 46030 | B7: THAYNA ELIZABETE GOMES DA SILVA | C7: =MONTH(Tabela16[[#This Row],[DATA]]) -> 1
A8: 46030 | B8: THEOGENES PAULO SESTREM PALOPOLI | C8: =MONTH(Tabela16[[#This Row],[DATA]]) -> 1
A9: 46030 | B9: THEOGENES PAULO SESTREM PALOPOLI | C9: =MONTH(Tabela16[[#This Row],[DATA]]) -> 1
A10: 46030 | B10: RENATA SILVA DE SOUSA | C10: =MONTH(Tabela16[[#This Row],[DATA]]) -> 1
A11: 46030 | B11: THAYNA ELIZABETE GOMES DA SILVA | C11: =MONTH(Tabela16[[#This Row],[DATA]]) -> 1
A12: 46031 | B12: THAYNA ELIZABETE GOMES DA SILVA | C12: =MONTH(Tabela16[[#This Row],[DATA]]) -> 1
A13: 46031 | B13: THEOGENES PAULO SESTREM PALOPOLI | C13: =MONTH(Tabela16[[#This Row],[DATA]]) -> 1
... A526: 46273 | B526: CARMINE AVARESE FILHO | C526: =MONTH(Tabela16[[#This Row],[DATA]]) -> 9
A527: 46273 | C527: =MONTH(Tabela16[[#This Row],[DATA]]) -> 9
A528: 46273 | B528: CARMINE AVARESE FILHO | C528: =MONTH(Tabela16[[#This Row],[DATA]]) -> 9
A529: 46273 | B529: CARMINE AVARESE FILHO | C529: =MONTH(Tabela16[[#This Row],[DATA]]) -> 9
A530: 46273 | B530: CARMINE AVARESE FILHO | C530: =MONTH(Tabela16[[#This Row],[DATA]]) -> 9
A531: 46275 | B531: CARMINE AVARESE FILHO | C531: =MONTH(Tabela16[[#This Row],[DATA]]) -> 9
A532: 46275 | B532: ARTHUR GOMES | C532: =MONTH(Tabela16[[#This Row],[DATA]]) -> 9
A533: 46275 | B533: ANDRE MENDES DE SOUSA | C533: =MONTH(Tabela16[[#This Row],[DATA]]) -> 9
A534: 46276 | B534: ALEXANDRE MORAIS MEDEIROS DA SILVA | C534: =MONTH(Tabela16[[#This Row],[DATA]]) -> 9
A535: 46276 | B535: CARMINE AVARESE FILHO | C535: =MONTH(Tabela16[[#This Row],[DATA]]) -> 9
A536: 46276 | B536: CARMINE AVARESE FILHO | C536: =MONTH(Tabela16[[#This Row],[DATA]]) -> 9
A537: 46276 | B537: DEYVISON BRUNO CUTRIM FERREIRA | C537: =MONTH(Tabela16[[#This Row],[DATA]]) -> 9
A538: 46276 | B538: ARTHUR GOMES | C538: =MONTH(Tabela16[[#This Row],[DATA]]) -> 9
A539: 46276 | B539: DEYVISON BRUNO CUTRIM FERREIRA | C539: =MONTH(Tabela16[[#This Row],[DATA]]) -> 9
... A672: 46323 | B672: ARTHUR GOMES | C672: =MONTH(Tabela16[[#This Row],[DATA]]) -> 10

Sheet LIBERADO COMERCIAL
A1: COD_PREDIO | B1: CLUSTER | C1: TIPO_ID | D1: ESTEIRA | E1: dat_LibComercial | F1: AT | G1: nom_End | H1: val_Numero | I1: CABO | J1: PRIMARIA | K1: CONT | L1: LOCAL /ANDAR | M1: Data visita Gestor | N1: GESTOR | O1: Status | P1: Validação Gestão | Q1: Formalizado | R1: Retorno Implantação | S1: Validado | T1: Pendente | U1: Nok | V1: Acesso Negado | W1: Ano | X1: Semana | Y1: Flag_Mês | Z1: Flag_Dia | AA1: Column27 | AB1: MÊS
A2: 853745 | B2: SP/Paulista-Jardins | C2: ALÍVIO | D2: Liberado Comercial | E2: 46140 | F2: JD | G2: Alameda Casa Branca - lado ímpar | H2: 923 | I2: JDF#10 | J2: 43 | K2: 41-48 | 49-56 | L2: 1° / 6° | M2: 45786 | N2: ANDRE MENDES DE SOUSA | O2: NOK | P2: OK | R2: CORRIGIDO | S2: 1 | T2: 0 | U2: 1 | V2: 0 | W2: 2026 | X2: 18 | Y2: 4 | Z2: 28 | AB2: =MONTH(M2) -> 5
A3: 1502648 | B3: SP/Paulista-Jardins | C3: ALIVIO | D3: Liberado Comercial | E3: 46226 | F3: PA | G3: Avenida Paulista - de 2134 ao fim - lado par | H3: 2202 | I3: PAF#16 | J3: 31 | K3: 1-8 | 9-16 | 17-24 | 25-32 | 33-40 | 41-48 | 49-56 | L3: Galeria | 5° | 7° | M3: 45872 | N3: ANDRE MENDES DE SOUSA | O3: OK | P3: OK | S3: 1 | T3: 0 | U3: 0 | V3: 0 | W3: 2026 | X3: 30 | Y3: 7 | Z3: 23 | AB3: =MONTH(M3) -> 8
A4: 1356392 | B4: SP/Paulista-Jardins | C4: ALÍVIO | D4: Liberado Comercial | E4: 46055 | F4: IB | G4: Rua José Maria Lisboa | H4: 591 | I4: IBF#09 | J4: 19 | K4: 33 - 40 | 41 - 48 | M4: 46057 | N4: PRISCILA DE MELO SEVILHA ZANDELI | O4: OK | P4: Atenuado - Encaminhado E-mail | S4: 0 | T4: 0 | U4: 0 | V4: 0 | W4: 2026 | X4: 6 | Y4: 2 | Z4: 2 | AB4: =MONTH(M4) -> 2
A5: 55753 | B5: SP/Paulista-Jardins | C5: CONECTADOS | D5: Liberado Comercial | E5: 46055 | F5: PD | G5: Rua Gustavo Teixeira | H5: 342 | I5: PDF#01 | J5: 79 | K5: 17-24 | 25 - 32 | 33 - 40 | M5: 46065 | N5: CARMINE AVARESE FILHO | O5: OK | P5: OK | S5: 1 | T5: 0 | U5: 0 | V5: 0 | W5: 2026 | X5: 6 | Y5: 2 | Z5: 2 | AB5: =MONTH(M5) -> 2
A6: 1425699 | B6: SP/Paulista-Jardins | C6: CONECTADOS | D6: Liberado Comercial | E6: 46055 | F6: PD | G6: Rua Capote Valente | H6: 1300 | I6: PDF#08 | J6: 99 | K6: 33-40 | 49-56 | M6: 46065 | N6: CARMINE AVARESE FILHO | O6: NÃO AUTORIZADO | P6: OK | S6: 1 | T6: 0 | U6: 0 | V6: 1 | W6: 2026 | X6: 6 | Y6: 2 | Z6: 2 | AB6: =MONTH(M6) -> 2
A7: 1449656 | B7: SP/Paulista-Jardins | C7: ALÍVIO | D7: Liberado Comercial | E7: 46045 | F7: IB | G7: Rua Bastos Pereira | H7: 55 | I7: IBFH#04 | J7: 89 | K7: 01-08 | 09-16 | 17-24 | 25-32 | 33-40 | 41-48 | 49-56 | 57-64 | M7: 46066 | N7: DENIS REIS | O7: OK | P7: 2 SS com sinal atenuado | S7: 0 | T7: 0 | U7: 0 | V7: 0 | W7: 2026 | X7: 4 | Y7: 1 | Z7: 23 | AB7: =MONTH(M7) -> 2
A8: 1497385 | B8: SP/Paulista-Jardins | C8: ALÍVIO | D8: Liberado Comercial | E8: 46055 | F8: IM | G8: Rua Afonso Braz | H8: 693 | I8: IMFH#05 | J8: 101 | K8: 01 - 08 | M8: 46069 | N8: AFONSO HENRIQUES MIGUEL MOREIRA | O8: OK | P8: PENDENTE | S8: 0 | T8: 1 | U8: 0 | V8: 0 | W8: 2026 | X8: 6 | Y8: 2 | Z8: 2 | AB8: =MONTH(M8) -> 2
A9: 1369405 | B9: SP/Paulista-Jardins | C9: CONECTADOS | D9: Liberado Comercial | E9: 46055 | F9: VM | G9: Rua Machado Bitencourt | H9: 420 | I9: VMFH#12 | J9: 81 | K9: 01 - 64 | M9: 46069 | N9: DEYVISON BRUNO CUTRIM FERREIRA | O9: OK | P9: OK | S9: 1 | T9: 0 | U9: 0 | V9: 0 | W9: 2026 | X9: 6 | Y9: 2 | Z9: 2 | AB9: =MONTH(M9) -> 2
A10: 1369405 | B10: SP/Paulista-Jardins | C10: CONECTADOS | D10: Liberado Comercial | E10: 46055 | F10: VM | G10: Rua Machado Bitencourt | H10: 420 | I10: VMFH#12 | J10: 85 | K10: 01 - 64 | M10: 46069 | N10: DEYVISON BRUNO CUTRIM FERREIRA | O10: OK | P10: OK | S10: 1 | T10: 0 | U10: 0 | V10: 0 | W10: 2026 | X10: 6 | Y10: 2 | Z10: 2 | AB10: =MONTH(M10) -> 2
A11: 1369405 | B11: SP/Paulista-Jardins | C11: CONECTADOS | D11: Liberado Comercial | E11: 46055 | F11: VM | G11: Rua Machado Bitencourt | H11: 420 | I11: VMFH#12 | J11: 83 | K11: 33 - 40 | 41 - 48 | M11: 46069 | N11: DEYVISON BRUNO CUTRIM FERREIRA | O11: OK | P11: OK | S11: 1 | T11: 0 | U11: 0 | V11: 0 | W11: 2026 | X11: 6 | Y11: 2 | Z11: 2 | AB11: =MONTH(M11) -> 2
A12: 1395518 | B12: SP/Paulista-Jardins | C12: CONECTADOS | D12: Liberado Comercial | E12: 46055 | F12: IM | G12: Rua Bueno Brandão | H12: 257 | I12: IMFH#04 | J12: 58 | K12: SS4-6 | M12: 46069 | N12: AFONSO HENRIQUES MIGUEL MOREIRA | O12: NOK | P12: PENDENTE INSTALAÇÃO | S12: 0 | T12: 0 | U12: 1 | V12: 0 | W12: 2026 | X12: 6 | Y12: 2 | Z12: 2 | AB12: =MONTH(M12) -> 2
A13: 1395518 | B13: SP/Paulista-Jardins | C13: CONECTADOS | D13: Liberado Comercial | E13: 46055 | F13: IM | G13: Rua Bueno Brandão | H13: 257 | I13: IMFH#04 | J13: 51 | K13: SS7 - 8 | M13: 46069 | N13: DENIS REIS | O13: NOK | P13: PENDENTE INSTALAÇÃO | S13: 0 | T13: 0 | U13: 1 | V13: 0 | W13: 2026 | X13: 6 | Y13: 2 | Z13: 2 | AB13: =MONTH(M13) -> 2
A14: 1407284 | B14: SP/Paulista-Jardins | C14: CONECTADOS | D14: Liberado Comercial | E14: 46059 | F14: VM | G14: Rua Manuel de Paiva | H14: 128 | I14: VMFH#16 | J14: 47 | K14: 01 - 32 | M14: 46069 | N14: DEYVISON BRUNO CUTRIM FERREIRA | O14: OK | P14: OK | S14: 1 | T14: 0 | U14: 0 | V14: 0 | W14: 2026 | X14: 6 | Y14: 2 | Z14: 6 | AB14: =MONTH(M14) -> 2
A15: 1407284 | B15: SP/Paulista-Jardins | C15: CONECTADOS | D15: Liberado Comercial | E15: 46059 | F15: VM | G15: Rua Manuel de Paiva | H15: 128 | I15: VMFH#16 | J15: 45 | K15: 01 - 64 | M15: 46069 | N15: DEYVISON BRUNO CUTRIM FERREIRA | O15: OK | P15: OK | S15: 1 | T15: 0 | U15: 0 | V15: 0 | W15: 2026 | X15: 6 | Y15: 2 | Z15: 6 | AB15: =MONTH(M15) -> 2
... A19: 1485904 | B19: SP/Paulista-Jardins | C19: CONECTADOS | D19: Liberado Comercial | E19: 46059 | F19: PA | G19: Alameda Santos | H19: 211 | I19: PAFH04 | J19: 114 | K19: 17-24 | M19: 46076 | N19: HUMBERTO DE FARIA COSTA | O19: OK | P19: OK | S19: 1 | T19: 0 | U19: 0 | V19: 0 | W19: 2026 | X19: 6 | Y19: 2 | Z19: 6 | AB19: =MONTH(M19) -> 2
A20: 1422308 | B20: SP/Paulista-Jardins | C20: CONECTADOS | D20: Liberado Comercial | E20: 46064 | F20: PA | G20: Rua Maestro Cardim | H20: 1074 | M20: 46076 | N20: HUMBERTO DE FARIA COSTA | O20: OK | P20: OK | S20: 1 | T20: 0 | U20: 0 | V20: 0 | W20: 2026 | X20: 7 | Y20: 2 | Z20: 11 | AB20: =MONTH(M20) -> 2
A21: 1218659 | B21: SP/Paulista-Jardins | C21: CONECTADOS | D21: Liberado Comercial | E21: 46064 | F21: PA | G21: RUA LEONCIO DE CARVALHO | H21: 201 | M21: 46076 | N21: HUMBERTO DE FARIA COSTA | O21: NÃO AUTORIZADO | P21: OK | S21: 1 | T21: 0 | U21: 0 | V21: 1 | W21: 2026 | X21: 7 | Y21: 2 | Z21: 11 | AB21: =MONTH(M21) -> 2
A22: 1407183 | B22: SP/Paulista-Jardins | C22: CONECTADOS | D22: Liberado Comercial | E22: 46063 | F22: JD | G22: Rua Fradique Coutinho | H22: 262 | I22: JDFH#05 | J22: 27 | K22: 01 - 40 | M22: 46090 | N22: HUMBERTO DE FARIA COSTA | O22: OK | P22: CDOI atenuado | Q22: 46091 | R22: Fora do prazo da garantia | S22: 0 | T22: 0 | U22: 0 | V22: 0 | W22: 2026 | X22: 7 | Y22: 2 | Z22: 10 | AB22: =MONTH(M22) -> 3
A23: 1407183 | B23: SP/Paulista-Jardins | C23: CONECTADOS | D23: Liberado Comercial | E23: 46064 | F23: PI | G23: Rua Fradique Coutinho | H23: 262 | I23: JDFH#05 | J23: 108 | K23: 01 - 64 | M23: 46090 | N23: HUMBERTO DE FARIA COSTA | O23: OK | P23: OK | S23: 1 | T23: 0 | U23: 0 | V23: 0 | W23: 2026 | X23: 7 | Y23: 2 | Z23: 11 | AB23: =MONTH(M23) -> 3
A24: 1106195 | B24: SP/Paulista-Jardins | C24: CONECTADOS | D24: Liberado Comercial | E24: 46059 | F24: JD | G24: Alameda Franca | H24: 895 | I24: JDFH#08 | J24: 97 | K24: 01 - 08 | M24: 46091 | N24: HUMBERTO DE FARIA COSTA | O24: NÃO AUTORIZADO | P24: OK | S24: 1 | T24: 0 | U24: 0 | V24: 1 | W24: 2026 | X24: 6 | Y24: 2 | Z24: 6 | AB24: =MONTH(M24) -> 3
A25: 1497136 | B25: SP/Paulista-Jardins | C25: ALÍVIO | D25: Liberado Comercial | E25: 46059 | F25: JD | G25: Alameda Franca | H25: 1633 | I25: JDFH#09 | J25: 53 | K25: 25 - 48 | M25: 46091 | N25: HUMBERTO DE FARIA COSTA | O25: Ok | P25: OK | S25: 1 | T25: 0 | U25: 0 | V25: 0 | W25: 2026 | X25: 6 | Y25: 2 | Z25: 6 | AB25: =MONTH(M25) -> 3
A26: 37004 | B26: SP/Paulista-Jardins | C26: ALÍVIO | D26: Liberado Comercial | E26: 46055 | F26: JD | G26: Rua Capote Valente | H26: 725 | I26: JDF#06 | J26: 68 | K26: SS3-SS4-SS5 | M26: 46097 | N26: HUMBERTO DE FARIA COSTA | O26: NÃO AUTORIZADO | P26: OK | S26: 1 | T26: 0 | U26: 0 | V26: 1 | W26: 2026 | X26: 6 | Y26: 2 | Z26: 2 | AB26: =MONTH(M26) -> 3
A27: 65280 | B27: SP/Paulista-Jardins | C27: ALÍVIO | D27: Liberado Comercial | E27: 46066 | F27: PI | G27: Rua Cardeal Arcoverde | H27: 1972 | M27: 46097 | N27: HUMBERTO DE FARIA COSTA | O27: Ok | P27: OK | S27: 1 | T27: 0 | U27: 0 | V27: 0 | W27: 2026 | X27: 7 | Y27: 2 | Z27: 13 | AB27: =MONTH(M27) -> 3
A28: 1423862 | B28: SP/Paulista-Jardins | C28: ALÍVIO | D28: Liberado Comercial | E28: 46027 | F28: VM | G28: Rua Borges Lagoa | H28: 933 | I28: VMFH#15 | J28: 35 | K28: 25-32 | M28: 46098 | N28: HUMBERTO DE FARIA COSTA | O28: OK | P28: OK | S28: 1 | T28: 0 | U28: 0 | V28: 0 | W28: 2026 | X28: 2 | Y28: 1 | Z28: 5 | AB28: =MONTH(M28) -> 3
A29: 1497383 | B29: SP/Paulista-Jardins | C29: ALÍVIO | D29: Liberado Comercial | E29: 46055 | F29: VM | G29: Rua Borges Lagoa | H29: 947 | I29: VMFH#15 | J29: 35 | K29: 01 - 08 | M29: 46098 | N29: HUMBERTO DE FARIA COSTA | O29: OK | P29: OK | S29: 1 | T29: 0 | U29: 0 | V29: 0 | W29: 2026 | X29: 6 | Y29: 2 | Z29: 2 | AB29: =MONTH(M29) -> 3
A30: 1432640 | B30: SP/Paulista-Jardins | C30: CONECTADOS | D30: Liberado Comercial | E30: 46055 | F30: VM | G30: Rua Borges Lagoa | H30: 564 | I30: VMFH#12 | J30: 137 | K30: 1-8 | M30: 46098 | N30: HUMBERTO DE FARIA COSTA | O30: OK | P30: OK | S30: 1 | T30: 0 | U30: 0 | V30: 0 | W30: 2026 | X30: 6 | Y30: 2 | Z30: 2 | AB30: =MONTH(M30) -> 3
A31: 1470141 | B31: SP/Paulista-Jardins | C31: CONECTADOS | D31: Liberado Comercial | E31: 46055 | F31: JD | G31: Rua Oscar Freire | H31: 1351 | I31: JDFH#06 | J31: 140 | K31: 41 - 48 | M31: 46099 | N31: HUMBERTO DE FARIA COSTA | O31: OK | P31: OK | S31: 1 | T31: 0 | U31: 0 | V31: 0 | W31: 2026 | X31: 6 | Y31: 2 | Z31: 2 | AB31: =MONTH(M31) -> 3
A32: 1322985 | B32: SP/Paulista-Jardins | C32: CONECTADOS | D32: Liberado Comercial | E32: 46041 | F32: PD | G32: Rua Xerentes | H32: 66 | I32: PDFH#09 | J32: 113 | K32: 49-56 | M32: 46100 | N32: HUMBERTO DE FARIA COSTA | O32: NÃO AUTORIZADO | P32: OK | S32: 1 | T32: 0 | U32: 0 | V32: 1 | W32: 2026 | X32: 4 | Y32: 1 | Z32: 19 | AB32: =MONTH(M32) -> 3
A33: 1497834 | B33: SP/Paulista-Jardins | C33: CONECTADOS | D33: Liberado Comercial | E33: 46059 | F33: VM | G33: Avenida Onze de Junho | H33: 220 | I33: VMFH#12 | J33: 87 | K33: 01- 32 | M33: 46101 | N33: HUMBERTO DE FARIA COSTA | O33: NÃO AUTORIZADO | P33: OK | S33: 1 | T33: 0 | U33: 0 | V33: 1 | W33: 2026 | X33: 6 | Y33: 2 | Z33: 6 | AB33: =MONTH(M33) -> 3
A34: 1497834 | B34: SP/Paulista-Jardins | C34: CONECTADOS | D34: Liberado Comercial | E34: 46059 | F34: VM | G34: Avenida Onze de Junho | H34: 220 | I34: VMFH#12 | J34: 83 | K34: 49 - 56 | 57 - 64 | M34: 46101 | N34: HUMBERTO DE FARIA COSTA | O34: NÃO AUTORIZADO | P34: OK | S34: 1 | T34: 0 | U34: 0 | V34: 1 | W34: 2026 | X34: 6 | Y34: 2 | Z34: 6 | AB34: =MONTH(M34) -> 3
A35: 1453236 | B35: SP/Paulista-Jardins | C35: ALÍVIO | D35: Liberado Comercial | E35: 46091 | F35: PD | G35: Rua Cotoxó | H35: 105 | I35: PDFH#11 | J35: 109 | K35: COMPLETA | L35: N. INFORMADO | M35: 46101 | N35: HUMBERTO DE FARIA COSTA | O35: NÃO AUTORIZADO | P35: OK | S35: 1 | T35: 0 | U35: 0 | V35: 1 | W35: 2026 | X35: 11 | Y35: 3 | Z35: 10 | AB35: =MONTH(M35) -> 3
A36: 1453236 | B36: SP/Paulista-Jardins | C36: ALÍVIO | D36: Liberado Comercial | E36: 46091 | F36: PD | G36: Rua Cotoxó | H36: 105 | I36: PDFH#11 | J36: 110 | K36: COMPLETA | L36: N. INFORMADO | M36: 46101 | N36: HUMBERTO DE FARIA COSTA | O36: NÃO AUTORIZADO | P36: OK | S36: 1 | T36: 0 | U36: 0 | V36: 1 | W36: 2026 | X36: 11 | Y36: 3 | Z36: 10 | AB36: =MONTH(M36) -> 3
A37: 1453236 | B37: SP/Paulista-Jardins | C37: ALÍVIO | D37: Liberado Comercial | E37: 46091 | F37: PD | G37: Rua Cotoxó | H37: 105 | I37: PDFH#11 | J37: 111 | K37: COMPLETA | L37: N. INFORMADO | M37: 46101 | N37: HUMBERTO DE FARIA COSTA | O37: NÃO AUTORIZADO | P37: OK | S37: 1 | T37: 0 | U37: 0 | V37: 1 | W37: 2026 | X37: 11 | Y37: 3 | Z37: 10 | AB37: =MONTH(M37) -> 3
A38: 1463281 | B38: SP/Paulista-Jardins | C38: ALÍVIO | D38: Liberado Comercial | E38: 46092 | F38: VM | G38: Rua Doutor Diogo de Faria | H38: 648 | I38: VMFH#15 | J38: 77 | K38: 01-08 | L38: N. INFORMADO | M38: 46101 | N38: HUMBERTO DE FARIA COSTA | O38: OK | P38: OK | S38: 1 | T38: 0 | U38: 0 | V38: 0 | W38: 2026 | X38: 11 | Y38: 3 | Z38: 11 | AB38: =MONTH(M38) -> 3
A39: 1463366 | B39: SP/Paulista-Jardins | C39: ALÍVIO | D39: Liberado Comercial | E39: 46092 | F39: VM | G39: Rua Doutor Diogo de Faria | H39: 1202 | I39: VMFH#15 | J39: 74 | K39: 33-40 | 41-48 | L39: 9° | M39: 46101 | N39: HUMBERTO DE FARIA COSTA | O39: OK | P39: OK | S39: 1 | T39: 0 | U39: 0 | V39: 0 | W39: 2026 | X39: 11 | Y39: 3 | Z39: 11 | AB39: =MONTH(M39) -> 3
A40: 1463402 | B40: SP/Paulista-Jardins | C40: ALÍVIO | D40: Liberado Comercial | E40: 46093 | F40: VM | G40: Rua Doutor Diogo de Faria | H40: 539 | I40: VMFH#12 | J40: 133 | K40: 01 - 08 | 09 - 16 | 17 - 24 | 25 - 32 | L40: 5°/7° | M40: 46101 | N40: HUMBERTO DE FARIA COSTA | O40: ok | P40: ok | S40: 1 | T40: 0 | U40: 0 | V40: 0 | W40: 2026 | X40: 11 | Y40: 3 | Z40: 12 | AB40: =MONTH(M40) -> 3
A41: 1407194 | B41: SP/Paulista-Jardins | C41: ALÍVIO | D41: Liberado Comercial | E41: 46093 | F41: VM | G41: Rua Doutor Diogo de Faria | H41: 448 | I41: VMFH#15 | J41: 89 | K41: 25-32 | 33-40 | 41-48 | 49-56 | 57-64 | L41: N. INFORMADO | M41: 46101 | N41: HUMBERTO DE FARIA COSTA | O41: OK | P41: OK | S41: 1 | T41: 0 | U41: 0 | V41: 0 | W41: 2026 | X41: 11 | Y41: 3 | Z41: 12 | AB41: =MONTH(M41) -> 3
A42: 1494969 | B42: SP/Paulista-Jardins | C42: ALÍVIO | D42: Liberado Comercial | E42: 46094 | F42: PD | G42: Rua Cláudio | H42: 185 | I42: PDFH#11 | J42: 88 | K42: 41-48 | 49-56 | L42: 7°/14° | M42: 46101 | N42: HUMBERTO DE FARIA COSTA | O42: OK | P42: OK | S42: 1 | T42: 0 | U42: 0 | V42: 0 | W42: 2026 | X42: 11 | Y42: 3 | Z42: 13 | AB42: =MONTH(M42) -> 3
A43: 1494969 | B43: SP/Paulista-Jardins | C43: ALÍVIO | D43: Liberado Comercial | E43: 46094 | F43: PD | G43: Rua Cláudio | H43: 185 | I43: PDFH#11 | J43: 64 | K43: COMPLETA | L43: 3°/5°/7°/9°/11° | M43: 46101 | N43: HUMBERTO DE FARIA COSTA | O43: OK | P43: OK | S43: 1 | T43: 0 | U43: 0 | V43: 0 | W43: 2026 | X43: 11 | Y43: 3 | Z43: 13 | AB43: =MONTH(M43) -> 3
A44: 1441356 | B44: SP/Paulista-Jardins | C44: ALÍVIO | D44: Liberado Comercial | E44: 46055 | F44: VM | G44: Rua Santa Cruz | H44: 1021 | I44: VMF#13 | J44: 13 | K44: 01 - 08 | 09 - 16 | 17 - 24 | M44: 46104 | N44: HUMBERTO DE FARIA COSTA | O44: NOK | P44: Sinal atenuado | Q44: 46105 | R44: Fora do prazo da garantia | S44: 0 | T44: 0 | U44: 1 | V44: 0 | W44: 2026 | X44: 6 | Y44: 2 | Z44: 2 | AB44: =MONTH(M44) -> 3
A45: 1425215 | B45: SP/Paulista-Jardins | C45: CONECTADOS | D45: Liberado Comercial | E45: 46060 | F45: VM | G45: Rua Sena Madureira | H45: 273 | I45: VMFH#12 | J45: 143 | K45: 41-48 | 49-56 | 57-64 | M45: 46104 | N45: HUMBERTO DE FARIA COSTA | O45: NÃO AUTORIZADO | P45: OK | S45: 1 | T45: 0 | U45: 0 | V45: 1 | W45: 2026 | X45: 6 | Y45: 2 | Z45: 7 | AB45: =MONTH(M45) -> 3
A46: 1395515 | B46: SP/Paulista-Jardins | C46: ALÍVIO | D46: Liberado Comercial | E46: 46066 | F46: VM | G46: Rua Francisco de Vitória | H46: 74 | M46: 46104 | N46: HUMBERTO DE FARIA COSTA | O46: OK | P46: OK | S46: 1 | T46: 0 | U46: 0 | V46: 0 | W46: 2026 | X46: 7 | Y46: 2 | Z46: 13 | AB46: =MONTH(M46) -> 3
A47: 1489201 | B47: SP/Paulista-Jardins | C47: ALÍVIO | D47: Liberado Comercial | E47: 46092 | F47: VM | G47: Rua Rino Pieralini | H47: 126 | I47: VMFH#14 | J47: 125 | K47: 01-08 | L47: N. INFORMADO | M47: 46104 | N47: HUMBERTO DE FARIA COSTA | O47: OK | P47: OK | S47: 1 | T47: 0 | U47: 0 | V47: 0 | W47: 2026 | X47: 11 | Y47: 3 | Z47: 11 | AB47: =MONTH(M47) -> 3
A48: 1214655 | B48: SP/Paulista-Jardins | C48: ALÍVIO | D48: Liberado Comercial | E48: 46093 | F48: VM | G48: Avenida Conselheiro Rodrigues Alves | H48: 1213 | I48: VMFH#15 | J48: 77 | K48: 01-08 | L48: DGOI CENTRAL | M48: 46104 | N48: HUMBERTO DE FARIA COSTA | O48: NÃO AUTORIZADO | P48: OK | S48: 1 | T48: 0 | U48: 0 | V48: 1 | W48: 2026 | X48: 11 | Y48: 3 | Z48: 12 | AB48: =MONTH(M48) -> 3
A49: 1371342 | B49: SP/Paulista-Jardins | C49: CONECTADOS | D49: Liberado Comercial | E49: 46059 | F49: JD | G49: Alameda Santos | H49: 2335 | I49: JDFH08 | J49: 92 | K49: 33 - 40 | M49: 46105 | N49: HUMBERTO DE FARIA COSTA | O49: NÃO AUTORIZADO | P49: OK | S49: 1 | T49: 0 | U49: 0 | V49: 1 | W49: 2026 | X49: 6 | Y49: 2 | Z49: 6 | AB49: =MONTH(M49) -> 3
A50: 1486378 | B50: SP/Paulista-Jardins | C50: CONECTADOS | D50: Liberado Comercial | E50: 46062 | F50: VM | G50: Rua Capitão Macedo | H50: 171 | M50: 46105 | N50: HUMBERTO DE FARIA COSTA | O50: NÃO AUTORIZADO | P50: OK | S50: 1 | T50: 0 | U50: 0 | V50: 1 | W50: 2026 | X50: 7 | Y50: 2 | Z50: 9 | AB50: =MONTH(M50) -> 3
A51: 1493505 | B51: SP/Paulista-Jardins | C51: ALÍVIO | D51: Liberado Comercial | E51: 46055 | F51: JD | G51: Rua dos Pinheiros | H51: 1005 | I51: JDF#05 | J51: 11 | K51: 33 - 40 | M51: 46106 | N51: HUMBERTO DE FARIA COSTA | O51: OK | P51: OK | S51: 1 | T51: 0 | U51: 0 | V51: 0 | W51: 2026 | X51: 6 | Y51: 2 | Z51: 2 | AB51: =MONTH(M51) -> 3
A52: 1361130 | B52: SP/Paulista-Jardins | C52: ALÍVIO | D52: Liberado Comercial | E52: 46094 | F52: JD | G52: Rua Capitão Antônio Rosa | H52: 151 | I52: JDFH#01 | J52: 131 | K52: 01-08 | L52: 1° | M52: 46106 | N52: HUMBERTO DE FARIA COSTA | O52: OK | P52: OK | S52: 1 | T52: 0 | U52: 0 | V52: 0 | W52: 2026 | X52: 11 | Y52: 3 | Z52: 13 | AB52: =MONTH(M52) -> 3
A53: 1463669 | B53: SP/Paulista-Jardins | C53: ALÍVIO | D53: Liberado Comercial | E53: 46101 | F53: VM | G53: Rua Gaspar Lourenço | H53: 234 | I53: VMFH#06 | J53: 72 | K53: 09-16 | L53: 5° | M53: 46107 | N53: HUMBERTO DE FARIA COSTA | O53: OK | P53: OK | S53: 1 | T53: 0 | U53: 0 | V53: 0 | W53: 2026 | X53: 12 | Y53: 3 | Z53: 20 | AB53: =MONTH(M53) -> 3
A54: 715262 | B54: SP/Paulista-Jardins | C54: ALÍVIO | D54: Liberado Comercial | E54: 46101 | F54: VM | G54: Rua Santo Irineu | H54: 60 | I54: VMFH#12 | J54: 15 | K54: 33-40 | L54: 2° | M54: 46107 | N54: HUMBERTO DE FARIA COSTA | O54: OK | P54: OK | S54: 1 | T54: 0 | U54: 0 | V54: 0 | W54: 2026 | X54: 12 | Y54: 3 | Z54: 20 | AB54: =MONTH(M54) -> 3
A55: 1463370 | B55: SP/Paulista-Jardins | C55: ALÍVIO | D55: Liberado Comercial | E55: 46097 | F55: VM | G55: Rua Napoleão de Barros | H55: 566 | I55: VMFH#15 | J55: 77 | K55: 09-16 | L55: 11° | M55: 46108 | N55: HUMBERTO DE FARIA COSTA | O55: OK | P55: OK | S55: 1 | T55: 0 | U55: 0 | V55: 0 | W55: 2026 | X55: 12 | Y55: 3 | Z55: 16 | AB55: =MONTH(M55) -> 3
A56: 1463496 | B56: SP/Paulista-Jardins | C56: ALÍVIO | D56: Liberado Comercial | E56: 46098 | F56: VM | G56: Avenida Conselheiro Rodrigues Alves | H56: 429 | I56: VMFH#06 | J56: 30 | K56: 41-48 | L56: Térreo | M56: 46111 | N56: HUMBERTO DE FARIA COSTA | O56: OK | P56: OK | S56: 1 | T56: 0 | U56: 0 | V56: 0 | W56: 2026 | X56: 12 | Y56: 3 | Z56: 17 | AB56: =MONTH(M56) -> 3
A57: 13225 | B57: SP/Paulista-Jardins | C57: ALÍVIO | D57: Liberado Comercial | E57: 46100 | F57: VM | G57: Rua Joinville - de 401_402 ao fim | H57: 637 | I57: VMFH#17 | J57: 89 | K57: 01-08 | L57: 1° | M57: 46111 | N57: HUMBERTO DE FARIA COSTA | O57: OK | P57: OK | S57: 1 | T57: 0 | U57: 0 | V57: 0 | W57: 2026 | X57: 12 | Y57: 3 | Z57: 19 | AB57: =MONTH(M57) -> 3
A58: 1507332 | B58: SP/Paulista-Jardins | C58: ALÍVIO | D58: Liberado Comercial | E58: 46100 | F58: VM | G58: Rua Jaime Viana | H58: 14 | I58: VMFH#12 | J58: 63 | K58: completa | L58: Lado A 1,4,7,11| Lado B 1,4,7,10 | M58: 46111 | N58: HUMBERTO DE FARIA COSTA | O58: NOK | P58: Sinal atenuado | Q58: 46111 | R58: Irei encaminhar equipe | S58: 0 | T58: 0 | U58: 1 | V58: 0 | W58: 2026 | X58: 12 | Y58: 3 | Z58: 19 | AB58: =MONTH(M58) -> 3
A59: 1425296 | B59: SP/Paulista-Jardins | C59: ALÍVIO | D59: Liberado Comercial | E59: 46055 | F59: VM | G59: RUA CHARLES ASTOR | H59: 226 | I59: VMFH#13 | J59: 5 | K59: 01 - 64 | M59: 46112 | N59: HUMBERTO DE FARIA COSTA | O59: OK | P59: OK | S59: 1 | T59: 0 | U59: 0 | V59: 0 | W59: 2026 | X59: 6 | Y59: 2 | Z59: 2 | AB59: =MONTH(M59) -> 3
A60: 1425296 | B60: SP/Paulista-Jardins | C60: ALÍVIO | D60: Liberado Comercial | E60: 46055 | F60: VM | G60: RUA CHARLES ASTOR | H60: 226 | I60: VMFH#13 | J60: 7 | K60: 01 - 64 | M60: 46112 | N60: HUMBERTO DE FARIA COSTA | O60: OK | P60: OK | S60: 1 | T60: 0 | U60: 0 | V60: 0 | W60: 2026 | X60: 6 | Y60: 2 | Z60: 2 | AB60: =MONTH(M60) -> 3
A61: 1426288 | B61: SP/Paulista-Jardins | C61: ALÍVIO | D61: Liberado Comercial | E61: 46078 | F61: VM | G61: Rua Joaquim Távora - de 1142 a 1356 - lado par | H61: 1210 | I61: VMFH#05 | J61: 35 | K61: 49 - 56 | 57 - 64 | M61: 46112 | N61: HUMBERTO DE FARIA COSTA | O61: OK | P61: OK | S61: 1 | T61: 0 | U61: 0 | V61: 0 | W61: 2026 | X61: 9 | Y61: 2 | Z61: 25 | AB61: =MONTH(M61) -> 3
A62: 1463475 | B62: SP/Paulista-Jardins | C62: CONECTADOS | D62: Liberado Comercial | E62: 46056 | F62: VM | G62: Avenida Lins de Vasconcelos | H62: 2950 | I62: VMFH#14 | J62: 83 | K62: 01 - 64 | M62: 46113 | N62: HUMBERTO DE FARIA COSTA | O62: NOK | P62: Parcial sem sinal | Q62: 46119 | R62: Fora do prazo da garantia | S62: 0 | T62: 0 | U62: 1 | V62: 0 | W62: 2026 | X62: 6 | Y62: 2 | Z62: 3 | AB62: =MONTH(M62) -> 4
A63: 1444545 | B63: SP/Paulista-Jardins | C63: ALÍVIO | D63: Liberado Comercial | E63: 46099 | F63: PD | G63: Rua Cayowaa | H63: 854 | I63: PDFH#01 | J63: 105 | K63: 17-24 | L63: Térreo | M63: 46113 | N63: HUMBERTO DE FARIA COSTA | O63: NOK | P63: Sem Sinal | Q63: 46119 | R63: já possui cliente instalado | S63: 0 | T63: 0 | U63: 1 | V63: 0 | W63: 2026 | X63: 12 | Y63: 3 | Z63: 18 | AB63: =MONTH(M63) -> 4
A64: 1496317 | B64: SP/Paulista-Jardins | C64: ALÍVIO | D64: Liberado Comercial | E64: 46060 | F64: PD | G64: Praça Irmãos Karmann - Torre B | H64: 100 | I64: PDFH#13 | J64: 16 | K64: 01 - 08 | 09 - 16 | M64: 46118 | N64: HUMBERTO DE FARIA COSTA | O64: NÃO AUTORIZADO | P64: OK | S64: 1 | T64: 0 | U64: 0 | V64: 1 | W64: 2026 | X64: 6 | Y64: 2 | Z64: 7 | AB64: =MONTH(M64) -> 4
A65: 1496316 | B65: SP/Paulista-Jardins | C65: ALÍVIO | D65: Liberado Comercial | E65: 46060 | F65: PD | G65: Praça Irmãos Karmann - Torre A | H65: 100 | I65: PDFH#13 | J65: 16 | K65: 17 - 24 | M65: 46118 | N65: HUMBERTO DE FARIA COSTA | O65: NÃO AUTORIZADO | P65: OK | S65: 1 | T65: 0 | U65: 0 | V65: 1 | W65: 2026 | X65: 6 | Y65: 2 | Z65: 7 | AB65: =MONTH(M65) -> 4
A66: 1213436 | B66: SP/Paulista-Jardins | C66: ALÍVIO | D66: Liberado Comercial | E66: 46101 | F66: PI | G66: RUA MORAS | H66: 390 | I66: PIFH#07 | J66: 39 | K66: 09-16 | L66: Térreo | M66: 46118 | N66: HUMBERTO DE FARIA COSTA | O66: NÃO AUTORIZADO | P66: OK | S66: 1 | T66: 0 | U66: 0 | V66: 1 | W66: 2026 | X66: 12 | Y66: 3 | Z66: 20 | AB66: =MONTH(M66) -> 4
A67: 1444439 | B67: SP/Paulista-Jardins | C67: ALÍVIO | D67: Liberado Comercial | E67: 46099 | F67: PD | G67: Rua Cardoso de Almeida | H67: 60 | I67: PDFH#12 | J67: 59 | K67: 01-08 | L67: 1° | M67: 46119 | N67: HUMBERTO DE FARIA COSTA | O67: NOK | P67: Atenuado - Encaminhado E-mail | Q67: 46122 | S67: 0 | T67: 0 | U67: 1 | V67: 0 | W67: 2026 | X67: 12 | Y67: 3 | Z67: 18 | AB67: =MONTH(M67) -> 4
A68: 1444437 | B68: SP/Paulista-Jardins | C68: ALÍVIO | D68: Liberado Comercial | E68: 46101 | F68: PD | G68: Rua Cardoso de Almeida | H68: 23 | I68: PDFH#12 | J68: 59 | K68: 25-32 | L68: 1° | M68: 46119 | N68: HUMBERTO DE FARIA COSTA | O68: OK | P68: OK | S68: 1 | T68: 0 | U68: 0 | V68: 0 | W68: 2026 | X68: 12 | Y68: 3 | Z68: 20 | AB68: =MONTH(M68) -> 4
A69: 1463417 | B69: SP/Paulista-Jardins | C69: ALÍVIO | D69: Liberado Comercial | E69: 46118 | F69: VM | G69: Rua Berta | H69: 270 | I69: VMFH#14 | J69: 3 | K69: COMPLETA | M69: 46120 | N69: HUMBERTO DE FARIA COSTA | O69: OK | P69: OK | S69: 1 | T69: 0 | U69: 0 | V69: 0 | W69: 2026 | X69: 15 | Y69: 4 | Z69: 6 | AB69: =MONTH(M69) -> 4
A70: 1444551 | B70: SP/Paulista-Jardins | C70: ALÍVIO | D70: Liberado Comercial | E70: 46099 | F70: PD | G70: Rua Cayowaa | H70: 1027 | I70: PDFH#01 | J70: 122 | K70: 09-16 | L70: 10° | M70: 46122 | N70: HUMBERTO DE FARIA COSTA | O70: OK | P70: OK | S70: 1 | T70: 0 | U70: 0 | V70: 0 | W70: 2026 | X70: 12 | Y70: 3 | Z70: 18 | AB70: =MONTH(M70) -> 4
A71: 1444680 | B71: SP/Paulista-Jardins | C71: ALÍVIO | D71: Liberado Comercial | E71: 46101 | F71: PD | G71: Rua Melo Palheta | H71: 112 | I71: PDFH#04 | J71: 59 | K71: 33-40 | L71: Térreo | M71: 46122 | N71: HUMBERTO DE FARIA COSTA | O71: OK | P71: OK | S71: 1 | T71: 0 | U71: 0 | V71: 0 | W71: 2026 | X71: 12 | Y71: 3 | Z71: 20 | AB71: =MONTH(M71) -> 4
A72: 1500170 | B72: SP/Paulista-Jardins | C72: ALÍVIO | D72: Liberado Comercial | E72: 46118 | F72: VM | G72: Rua João Álvares Correia | H72: 136 | I72: VMFH#13 | J72: 59 | K72: 33-40 | 41-48 | 49-56 | 57-64 | M72: 46122 | N72: HUMBERTO DE FARIA COSTA | O72: OK | P72: OK | S72: 1 | T72: 0 | U72: 0 | V72: 0 | W72: 2026 | X72: 15 | Y72: 4 | Z72: 6 | AB72: =MONTH(M72) -> 4
A73: 1500170 | B73: SP/Paulista-Jardins | C73: ALÍVIO | D73: Liberado Comercial | E73: 46118 | F73: VM | G73: Rua João Álvares Correia | H73: 136 | I73: VMFH#13 | J73: 53 | K73: Completa | M73: 46122 | N73: HUMBERTO DE FARIA COSTA | O73: OK | P73: OK | S73: 1 | T73: 0 | U73: 0 | V73: 0 | W73: 2026 | X73: 15 | Y73: 4 | Z73: 6 | AB73: =MONTH(M73) -> 4
A74: 1500170 | B74: SP/Paulista-Jardins | C74: ALÍVIO | D74: Liberado Comercial | E74: 46118 | F74: VM | G74: Rua João Álvares Correia | H74: 136 | I74: VMFH#13 | J74: 55 | K74: Completa | M74: 46122 | N74: HUMBERTO DE FARIA COSTA | O74: OK | P74: OK | S74: 1 | T74: 0 | U74: 0 | V74: 0 | W74: 2026 | X74: 15 | Y74: 4 | Z74: 6 | AB74: =MONTH(M74) -> 4
A75: 1500170 | B75: SP/Paulista-Jardins | C75: ALÍVIO | D75: Liberado Comercial | E75: 46118 | F75: VM | G75: Rua João Álvares Correia | H75: 136 | I75: VMFH#13 | J75: 57 | K75: Completa | M75: 46122 | N75: HUMBERTO DE FARIA COSTA | O75: OK | P75: OK | S75: 1 | T75: 0 | U75: 0 | V75: 0 | W75: 2026 | X75: 15 | Y75: 4 | Z75: 6 | AB75: =MONTH(M75) -> 4
A76: 1485654 | B76: SP/Paulista-Jardins | C76: ALÍVIO | D76: Liberado Comercial | E76: 46055 | F76: PD | G76: Rua Iperoig | H76: 180 | I76: PDFH#13 | J76: 108 | K76: 49 - 56 | 57-64 | M76: 46126 | N76: HUMBERTO DE FARIA COSTA | O76: NÃO AUTORIZADO | P76: OK | S76: 1 | T76: 0 | U76: 0 | V76: 1 | W76: 2026 | X76: 6 | Y76: 2 | Z76: 2 | AB76: =MONTH(M76) -> 4
A77: 1447399 | B77: SP/Paulista-Jardins | C77: ALÍVIO | D77: Liberado Comercial | E77: 46118 | F77: HM | G77: Rua Joaquim Floriano | H77: 466 | I77: HMFH#04 | J77: 68 | K77: 25-32 | L77: 8° | M77: 46126 | N77: HUMBERTO DE FARIA COSTA | O77: OK | P77: OK | S77: 1 | T77: 0 | U77: 0 | V77: 0 | W77: 2026 | X77: 15 | Y77: 4 | Z77: 6 | AB77: =MONTH(M77) -> 4
A78: 1463300 | B78: SP/Paulista-Jardins | C78: ALÍVIO | D78: Liberado Comercial | E78: 46118 | F78: VM | G78: Rua Botucatu | H78: 572 | I78: VMFH#10 | J78: 61 | K78: 01-08 | M78: 46127 | N78: HUMBERTO DE FARIA COSTA | O78: OK | P78: OK | S78: 1 | T78: 0 | U78: 0 | V78: 0 | W78: 2026 | X78: 15 | Y78: 4 | Z78: 6 | AB78: =MONTH(M78) -> 4
A79: 1444526 | B79: SP/Paulista-Jardins | C79: ALÍVIO | D79: Liberado Comercial | E79: 46100 | F79: PD | G79: Rua Caiubi | H79: 372 | I79: PDFH#04 | J79: 124 | K79: 01-08 | L79: Térreo | M79: 46128 | N79: HUMBERTO DE FARIA COSTA | O79: OK | P79: OK | S79: 1 | T79: 0 | U79: 0 | V79: 0 | W79: 2026 | X79: 12 | Y79: 3 | Z79: 19 | AB79: =MONTH(M79) -> 4
A80: 1515962 | B80: SP/Paulista-Jardins | C80: ALÍVIO | D80: Liberado Comercial | E80: 46118 | F80: JD | G80: Avenida Doutor Arnaldo | H80: 355 | I80: JDFH#09 | J80: 25 | K80: 41-48 | L80: H.Clinicas | M80: 46129 | N80: CARMINE AVARESE FILHO | O80: OK | P80: OK | S80: 1 | T80: 0 | U80: 0 | V80: 0 | W80: 2026 | X80: 15 | Y80: 4 | Z80: 6 | AB80: =MONTH(M80) -> 4
A81: 1516416 | B81: SP/Paulista-Jardins | C81: ALÍVIO | D81: Liberado Comercial | E81: 46129 | F81: JD | G81: Avenida Doutor Arnaldo | H81: 455 | I81: JDFH#09 | J81: 25 | K81: 33-40 | L81: H.Clinicas | M81: 46129 | N81: CARMINE AVARESE FILHO | O81: OK | P81: OK | S81: 1 | T81: 0 | U81: 0 | V81: 0 | W81: 2026 | X81: 16 | Y81: 4 | Z81: 17 | AB81: =MONTH(M81) -> 4
A82: 1522781 | B82: SP/Paulista-Jardins | C82: ALÍVIO | D82: Liberado Comercial | E82: 46134 | F82: JD | G82: Rua Capote Valente | H82: 80 | I82: JDFH#07 | J82: 3 | K82: 49-56 | L82: 7° | M82: 46141 | N82: ALEXANDRE MORAIS MEDEIROS DA SILVA | O82: OK | P82: OK | S82: 1 | T82: 0 | U82: 0 | V82: 0 | W82: 2026 | X82: 17 | Y82: 4 | Z82: 22 | AB82: =MONTH(M82) -> 4
A83: 1536955 | B83: SP/Paulista-Jardins | C83: ALÍVIO | D83: Liberado Comercial | E83: 46136 | F83: JD | G83: AVENIDA DOUTOR ARNALDO | H83: 455 | I83: JDFH#09 | J83: 25 | K83: 33-40 | L83: TÉRREO | M83: 46142 | N83: ALEXANDRE MORAIS MEDEIROS DA SILVA | O83: OK | P83: OK | S83: 1 | T83: 0 | U83: 0 | V83: 0 | W83: 2026 | X83: 17 | Y83: 4 | Z83: 24 | AB83: =MONTH(M83) -> 4
A84: 1453124 | B84: SP/Paulista-Jardins | C84: ALÍVIO | D84: Liberado Comercial | E84: 46134 | F84: PI | G84: Rua Fernão Dias | H84: 370 | I84: PIF#01 | J84: 103 | K84: 01-08 | 09-16 | 17-24 | 25-32 | 33-40 | 41-48 | 49-56 | 57-64 | L84: 1° / 2° / 3° / 4° / 5° / 6 /° 7° / 8° | M84: 46146 | N84: NILTON CAMPOS DE BARROS | O84: OK | P84: OK | S84: 1 | T84: 0 | U84: 0 | V84: 0 | W84: 2026 | X84: 17 | Y84: 4 | Z84: 22 | AB84: =MONTH(M84) -> 5
A85: 1453124 | B85: SP/Paulista-Jardins | C85: ALÍVIO | D85: Liberado Comercial | E85: 46134 | F85: PI | G85: Rua Fernão Dias | H85: 370 | I85: PIF#01 | J85: 106 | K85: 01-08 | 09-16 | 17-24 | 25-32 | 33-40 | 41-48 | 49-56 | 57-64 | L85: 16° / 17° / 18° / 19° / 20° / 21° / 22° / 23° | M85: 46146 | N85: NILTON CAMPOS DE BARROS | O85: OK | P85: OK | S85: 1 | T85: 0 | U85: 0 | V85: 0 | W85: 2026 | X85: 17 | Y85: 4 | Z85: 22 | AB85: =MONTH(M85) -> 5
A86: 1453124 | B86: SP/Paulista-Jardins | C86: ALÍVIO | D86: Liberado Comercial | E86: 46134 | F86: PI | G86: Rua Fernão Dias | H86: 370 | I86: PIF#01 | J86: 104 | K86: 09-16 | 17-24 | 25-32 | 33-40 | 41-48 | 49-56 | 57-64 | L86: 9° / 10° / 11° / 12° / 13° / 14° / 15° | M86: 46146 | N86: NILTON CAMPOS DE BARROS | O86: OK | P86: OK | S86: 1 | T86: 0 | U86: 0 | V86: 0 | W86: 2026 | X86: 17 | Y86: 4 | Z86: 22 | AB86: =MONTH(M86) -> 5
A87: 1489478 | B87: SP/Paulista-Jardins | C87: ALÍVIO | D87: Liberado Comercial | E87: 46134 | F87: VM | G87: Rua Luís Molina | H87: 125 | I87: VMFH#13 | J87: 27 | K87: 01-08 | 09-16 | 17-24 | 25-32 | L87: 2° / 3° / 5° / 7° | M87: 46147 | N87: HUMBERTO DE FARIA COSTA | O87: NÃO AUTORIZADO | P87: OK | S87: 1 | T87: 0 | U87: 0 | V87: 1 | W87: 2026 | X87: 17 | Y87: 4 | Z87: 22 | AB87: =MONTH(M87) -> 5
A88: 1463408 | B88: SP/Paulista-Jardins | C88: ALÍVIO | D88: Liberado Comercial | E88: 46134 | F88: VM | G88: Rua Madre Cabrini | H88: 314 | I88: VMF#14 | J88: 53 | K88: 17-24 | 25-32 | L88: 5° / 9° | M88: 46147 | N88: HUMBERTO DE FARIA COSTA | O88: NOK | P88: Atenuado | R88: CORRIGIDO | S88: 0 | T88: 0 | U88: 1 | V88: 0 | W88: 2026 | X88: 17 | Y88: 4 | Z88: 22 | AB88: =MONTH(M88) -> 5
A89: 1463430 | B89: SP/Paulista-Jardins | C89: ALÍVIO | D89: Liberado Comercial | E89: 46136 | F89: VM | G89: Rua Domingos Augusto Setti | H89: 247 | I89: VMFH#13 | J89: 19 | K89: 01-08 | 09-16 | 17-24 |25-32 | 33-40 | 41-48 | 49-56 | 57-64 | L89: 24° / 17° | M89: 46147 | N89: HUMBERTO DE FARIA COSTA | O89: OK | P89: OK | S89: 1 | T89: 0 | U89: 0 | V89: 0 | W89: 2026 | X89: 17 | Y89: 4 | Z89: 24 | AB89: =MONTH(M89) -> 5
A90: 1463430 | B90: SP/Paulista-Jardins | C90: ALÍVIO | D90: Liberado Comercial | E90: 46136 | F90: VM | G90: Rua Domingos Augusto Setti | H90: 247 | I90: VMFH#13 | J90: 21 | K90: 01-09 | 09-16 |17-24 | 25-32 | 33-40 | 41-48 | 49-56 | 57-64 | L90: 10° / 6° | M90: 46147 | N90: HUMBERTO DE FARIA COSTA | O90: OK | P90: OK | S90: 1 | T90: 0 | U90: 0 | V90: 0 | W90: 2026 | X90: 17 | Y90: 4 | Z90: 24 | AB90: =MONTH(M90) -> 5
A91: 1463430 | B91: SP/Paulista-Jardins | C91: ALÍVIO | D91: Liberado Comercial | E91: 46136 | F91: VM | G91: Rua Domingos Augusto Setti | H91: 247 | I91: VMFH#13 | J91: 17 | K91: 33-40 | 41-48 | 49 -56 | 57-64 | L91: 33° | M91: 46147 | N91: HUMBERTO DE FARIA COSTA | O91: OK | P91: OK | S91: 1 | T91: 0 | U91: 0 | V91: 0 | W91: 2026 | X91: 17 | Y91: 4 | Z91: 24 | AB91: =MONTH(M91) -> 5
A92: 42811 | B92: SP/Paulista-Jardins | C92: ALÍVIO | D92: Liberado Comercial | E92: 46142 | F92: JD | G92: Rua Capote Valente - até 325_326 | H92: 65 | I92: JDF#07 | J92: 47 | K92: 1-8 | 9-17 | 17-24 | 25-32 | 33-40 |41-48 | 49-56 | 57-64 | L92: Torre 1 - 2°/ 3°/ 6°/ 9° - Torre 2° - 12°/15°/21°/24° | M92: 46150 | N92: PRISCILA DE MELO SEVILHA ZANDELI | O92: NÃO AUTORIZADO | P92: OK | S92: 1 | T92: 0 | U92: 0 | V92: 1 | W92: 2026 | X92: 18 | Y92: 4 | Z92: 30 | AB92: =MONTH(M92) -> 5
A93: 1514240 | B93: SP/Paulista-Jardins | C93: ALÍVIO | D93: Liberado Comercial | E93: 46140 | F93: JD | G93: Avenida Doutor Enéas Carvalho de Aguiar | H93: 647 | I93: JDFH#09 | J93: 26 | K93: 1-8 | 9-16 | L93: DG CENTRAL | M93: 46151 | N93: ANDRE MENDES DE SOUSA | O93: OK | P93: OK | R93: Cabista não conseguiu localizar a caixa, a pessoa que acompanhava não pode acompanhar | S93: 1 | T93: 0 | U93: 0 | V93: 0 | W93: 2026 | X93: 18 | Y93: 4 | Z93: 28 | AB93: =MONTH(M93) -> 5
A94: 1422284 | B94: SP/Paulista-Jardins | C94: ALÍVIO | D94: Liberado Comercial | E94: 46141 | F94: JD | G94: Rua Oscar Freire - até 608 - lado par | H94: 802 | I94: JDFH#09 | J94: 143 | K94: 33-40 | L94: 6° | M94: 46151 | N94: PRISCILA DE MELO SEVILHA ZANDELI | O94: NÃO AUTORIZADO | P94: OK | R94: Zelador negou a entrada e informou que não houve implantação | S94: 1 | T94: 0 | U94: 0 | V94: 1 | W94: 2026 | X94: 18 | Y94: 4 | Z94: 29 | AB94: =MONTH(M94) -> 5
A95: 1549581 | B95: SP/Paulista-Jardins | C95: ALÍVIO | D95: Liberado Comercial | E95: 46153 | F95: PA | G95: AL JAU 6680 | H95: 550 | I95: PAFH#16 | J95: 9 | K95: 1-8 | 9-17 | 17-24 | 25-32 | 33-40 |41-48 | 49-56 | 57-64 | L95: Esdudios - 2°/3°/4°/5°/6°/7°/8° | M95: 46167 | N95: CARMINE AVARESE FILHO | O95: OK | P95: OK | S95: 1 | T95: 0 | U95: 0 | V95: 0 | W95: 2026 | X95: 20 | Y95: 5 | Z95: 11 | AB95: =MONTH(M95) -> 5
A96: 877532 | B96: SP/Paulista-Jardins | C96: ALÍVIO | D96: Liberado Comercial | E96: 46153 | F96: PA | G96: AL JAU 6680 | H96: 550 | I96: PAFH#16 | J96: 7 | K96: 1-8 | 9-17 | 17-24 | 25-32 | 33-40 |41-48 | 49-56 | 57-64 | L96: Residencial - 11°/12°/13°/14°/15°/16°/17°/18° | M96: 46167 | N96: CARMINE AVARESE FILHO | O96: OK | P96: OK | S96: 1 | T96: 0 | U96: 0 | V96: 0 | W96: 2026 | X96: 20 | Y96: 5 | Z96: 11 | AB96: =MONTH(M96) -> 5
A97: 1427305 | B97: SP/Paulista-Jardins | C97: ALÍVIO | D97: Liberado Comercial | E97: 46154 | F97: PI | G97: Rua Fernão Dias - até 467 - lado ímpar | H97: 291 | I97: PIFH#01 | J97: 75 | K97: 49-57 | L97: DG CENTRAL | M97: 46167 | N97: NILTON CAMPOS DE BARROS | O97: OK | P97: OK | S97: 1 | T97: 0 | U97: 0 | V97: 0 | W97: 2026 | X97: 20 | Y97: 5 | Z97: 12 | AB97: =MONTH(M97) -> 5
A98: 1343461 | B98: SP/Paulista-Jardins | C98: ALÍVIO | D98: Liberado Comercial | E98: 46157 | F98: IB | G98: Rua Achilles Masetti | H98: 105 | I98: IBF#07 | J98: 132 | K98: 1-8 | 9-17 | 17-24 | 25-32 | L98: Torre 2 - 12°/16°/20° | M98: 46169 | N98: PRISCILA DE MELO SEVILHA ZANDELI | O98: OK | P98: OK | S98: 1 | T98: 0 | U98: 0 | V98: 0 | W98: 2026 | X98: 20 | Y98: 5 | Z98: 15 | AB98: =MONTH(M98) -> 5
A99: 1343462 | B99: SP/Paulista-Jardins | C99: ALÍVIO | D99: Liberado Comercial | E99: 46157 | F99: IB | G99: Rua Achilles Masetti | H99: 105 | I99: IBF#07 | J99: 131 | K99: 1-8 | 9-17 | 17-24 | 25-32 | 33-40 |41-48 | 49-56 | L99: Torre 1 - 1°/4°/8°/12°/16°/20° Torre 2 - 4° | M99: 46169 | N99: PRISCILA DE MELO SEVILHA ZANDELI | O99: OK | P99: OK | S99: 1 | T99: 0 | U99: 0 | V99: 0 | W99: 2026 | X99: 20 | Y99: 5 | Z99: 15 | AB99: =MONTH(M99) -> 5
A100: 1463481 | B100: SP/Paulista-Jardins | C100: ALÍVIO | D100: Liberado Comercial | E100: 46154 | F100: JD | G100: Rua Francisco Leitão | H100: 436 | I100: JDF#05 | J100: 111 | K100: 25-32|41-48|57-64 | L100: Lado B - 3°/6°/9° | M100: 46183 | N100: ALEXANDRE MORAIS MEDEIROS DA SILVA | O100: OK | P100: OK | S100: 1 | T100: 0 | U100: 0 | V100: 0 | W100: 2026 | X100: 20 | Y100: 5 | Z100: 12 | AB100: =MONTH(M100) -> 6
A101: 1551907 | B101: SP/Paulista-Jardins | C101: ALÍVIO | D101: Liberado Comercial | E101: 46154 | F101: JD | G101: Rua Francisco Leitão | H101: 436 | I101: JDF#05 | J101: 110 | K101: 9-16 | 25-32 | L101: Lado A - 9°/12° | M101: 46183 | N101: ALEXANDRE MORAIS MEDEIROS DA SILVA | O101: OK | P101: OK | S101: 1 | T101: 0 | U101: 0 | V101: 0 | W101: 2026 | X101: 20 | Y101: 5 | Z101: 12 | AB101: =MONTH(M101) -> 6
A102: 654396 | B102: SP/Paulista-Jardins | C102: ALIVIO | D102: Liberado Comercial | E102: 46181 | F102: PA | G102: Avenida Bernardino de Campos - lado ímpar | H102: 327 | I102: PAFH#17 | J102: 7 | K102: 01-08 | 09-16 | 17-24 | L102: 2|4|6 | M102: 46189 | N102: DEYVISON BRUNO CUTRIM FERREIRA | O102: OK | P102: OK | S102: 1 | T102: 0 | U102: 0 | V102: 0 | W102: 2026 | X102: 24 | Y102: 6 | Z102: 8 | AB102: =MONTH(M102) -> 6
A103: 1361146 | B103: SP/Paulista-Jardins | C103: ALIVIO | D103: Liberado Comercial | E103: 46182 | F103: JD | G103: Rua Capote Valente - de 607_608 a 1023_1024 | H103: 655 | I103: JDF#06 | J103: 61 | K103: 49-56 | 57-64 | L103: Lado A - 1 | Lado B - 2 | M103: 46189 | N103: ANDRE MENDES DE SOUSA | O103: OK | P103: OK | S103: 1 | T103: 0 | U103: 0 | V103: 0 | W103: 2026 | X103: 24 | Y103: 6 | Z103: 9 | AB103: =MONTH(M103) -> 6
...

Sheet CALENDÁRIO
A1: DATA | B1: DIA_SEM | C1: DU | D1: MÊS | E1: DU_ACUM | G1: DATE (D-1) | H1: DU | I1: IRR SAFRA
A2: 46023 | B2: =UPPER(TEXT(A2,"DDD")) -> QUI | C2: 0 | D2: =MONTH(A2) -> 1 | E2: 0 | G2: =TODAY()-1 -> 46323 | H2: =VLOOKUP(G2,A:E,5,0) -> 19 | I2: 14.5
A3: 46024 | B3: =UPPER(TEXT(A3,"DDD")) -> SEX | C3: 1 | D3: =MONTH(A3) -> 1 | E3: 1
A4: 46025 | B4: =UPPER(TEXT(A4,"DDD")) -> SÁB | C4: 0 | D4: =MONTH(A4) -> 1 | E4: 1
A5: 46026 | B5: =UPPER(TEXT(A5,"DDD")) -> DOM | C5: 0 | D5: =MONTH(A5) -> 1 | E5: 1
A6: 46027 | B6: =UPPER(TEXT(A6,"DDD")) -> SEG | C6: 1 | D6: =MONTH(A6) -> 1 | E6: 2 | G6: ATIVIDADE | H6: META-DIA | I6: COMPROMISSO D-1
A7: 46028 | B7: =UPPER(TEXT(A7,"DDD")) -> TER | C7: 1 | D7: =MONTH(A7) -> 1 | E7: 3 | G7: RIT | H7: 4 | I7: =H7*$H$2 -> 76
A8: 46029 | B8: =UPPER(TEXT(A8,"DDD")) -> QUA | C8: 1 | D8: =MONTH(A8) -> 1 | E8: 4 | G8: CHECKLIST | H8: 2 | I8: =H8*$H$2 -> 38
A9: 46030 | B9: =UPPER(TEXT(A9,"DDD")) -> QUI | C9: 1 | D9: =MONTH(A9) -> 1 | E9: 5 | G9: FALHA DE M.O | H9: - | I9: =I7*I2/100 -> 11.02
A10: 46031 | B10: =UPPER(TEXT(A10,"DDD")) -> SEX | C10: 1 | D10: =MONTH(A10) -> 1 | E10: 6 | G10: DEGRADAÇÃO REDE | H10: 4 | I10: =H10*$H$2 -> 76
A11: 46032 | B11: =UPPER(TEXT(A11,"DDD")) -> SÁB | C11: 0 | D11: =MONTH(A11) -> 1 | E11: 6 | G11: LANLAMENTO SD | H11: 2 | I11: =H11*$H$2 -> 38
A12: 46033 | B12: =UPPER(TEXT(A12,"DDD")) -> DOM | C12: 0 | D12: =MONTH(A12) -> 1 | E12: 6 | G12: CLEAN-UP | H12: 0.5 | I12: =H12*$H$2 -> 9.5
A13: 46034 | B13: =UPPER(TEXT(A13,"DDD")) -> SEG | C13: 1 | D13: =MONTH(A13) -> 1 | E13: 7 | G13: MATERIAL INDEVIDO | H13: 4 | I13: =H13*$H$2 -> 76
A14: 46035 | B14: =UPPER(TEXT(A14,"DDD")) -> TER | C14: 1 | D14: =MONTH(A14) -> 1 | E14: 8 | G14: LIBERADO COMERCIAL | H14: 0 | I14: =H14*$H$2 -> 0
A15: 46036 | B15: =UPPER(TEXT(A15,"DDD")) -> QUA | C15: 1 | D15: =MONTH(A15) -> 1 | E15: 9
A16: 46037 | B16: =UPPER(TEXT(A16,"DDD")) -> QUI | C16: 1 | D16: =MONTH(A16) -> 1 | E16: 10
A17: 46038 | B17: =UPPER(TEXT(A17,"DDD")) -> SEX | C17: 1 | D17: =MONTH(A17) -> 1 | E17: 11
A18: 46039 | B18: =UPPER(TEXT(A18,"DDD")) -> SÁB | C18: 0 | D18: =MONTH(A18) -> 1 | E18: 11
A19: 46040 | B19: =UPPER(TEXT(A19,"DDD")) -> DOM | C19: 0 | D19: =MONTH(A19) -> 1 | E19: 11
A20: 46041 | B20: =UPPER(TEXT(A20,"DDD")) -> SEG | C20: 1 | D20: =MONTH(A20) -> 1 | E20: 12
A21: 46042 | B21: =UPPER(TEXT(A21,"DDD")) -> TER | C21: 1 | D21: =MONTH(A21) -> 1 | E21: 13
A22: 46043 | B22: =UPPER(TEXT(A22,"DDD")) -> QUA | C22: 1 | D22: =MONTH(A22) -> 1 | E22: 14
A23: 46044 | B23: =UPPER(TEXT(A23,"DDD")) -> QUI | C23: 1 | D23: =MONTH(A23) -> 1 | E23: 15
A24: 46045 | B24: =UPPER(TEXT(A24,"DDD")) -> SEX | C24: 1 | D24: =MONTH(A24) -> 1 | E24: 16
A25: 46046 | B25: =UPPER(TEXT(A25,"DDD")) -> SÁB | C25: 0 | D25: =MONTH(A25) -> 1 | E25: 16
A26: 46047 | B26: =UPPER(TEXT(A26,"DDD")) -> DOM | C26: 0 | D26: =MONTH(A26) -> 1 | E26: 16
... A274: 46295 | B274: =UPPER(TEXT(A274,"DDD")) -> QUA | C274: 1 | D274: =MONTH(A274) -> 9 | E274: 21
A275: 46296 | B275: =UPPER(TEXT(A275,"DDD")) -> QUI | C275: 1 | D275: =MONTH(A275) -> 10 | E275: =Tabela5[[#This Row],[DU]] -> 1
A276: 46297 | B276: =UPPER(TEXT(A276,"DDD")) -> SEX | C276: 1 | D276: =MONTH(A276) -> 10 | E276: =Tabela5[[#This Row],[DU]]+E275 -> 2
A277: 46298 | B277: =UPPER(TEXT(A277,"DDD")) -> SÁB | C277: 0 | D277: =MONTH(A277) -> 10 | E277: =Tabela5[[#This Row],[DU]]+E276 -> 2
A278: 46299 | B278: =UPPER(TEXT(A278,"DDD")) -> DOM | C278: 0 | D278: =MONTH(A278) -> 10 | E278: =Tabela5[[#This Row],[DU]]+E277 -> 2
A279: 46300 | B279: =UPPER(TEXT(A279,"DDD")) -> SEG | C279: 1 | D279: =MONTH(A279) -> 10 | E279: =Tabela5[[#This Row],[DU]]+E278 -> 3
A280: 46301 | B280: =UPPER(TEXT(A280,"DDD")) -> TER | C280: 1 | D280: =MONTH(A280) -> 10 | E280: =Tabela5[[#This Row],[DU]]+E279 -> 4
A281: 46302 | B281: =UPPER(TEXT(A281,"DDD")) -> QUA | C281: 1 | D281: =MONTH(A281) -> 10 | E281: =Tabela5[[#This Row],[DU]]+E280 -> 5
A282: 46303 | B282: =UPPER(TEXT(A282,"DDD")) -> QUI | C282: 1 | D282: =MONTH(A282) -> 10 | E282: =Tabela5[[#This Row],[DU]]+E281 -> 6
A283: 46304 | B283: =UPPER(TEXT(A283,"DDD")) -> SEX | C283: 1 | D283: =MONTH(A283) -> 10 | E283: =Tabela5[[#This Row],[DU]]+E282 -> 7
A284: 46305 | B284: =UPPER(TEXT(A284,"DDD")) -> SÁB | C284: 0 | D284: =MONTH(A284) -> 10 | E284: =Tabela5[[#This Row],[DU]]+E283 -> 7
A285: 46306 | B285: =UPPER(TEXT(A285,"DDD")) -> DOM | C285: 0 | D285: =MONTH(A285) -> 10 | E285: =Tabela5[[#This Row],[DU]]+E284 -> 7
A286: 46307 | B286: =UPPER(TEXT(A286,"DDD")) -> SEG | C286: 0 | D286: =MONTH(A286) -> 10 | E286: =Tabela5[[#This Row],[DU]]+E285 -> 7
A287: 46308 | B287: =UPPER(TEXT(A287,"DDD")) -> TER | C287: 1 | D287: =MONTH(A287) -> 10 | E287: =Tabela5[[#This Row],[DU]]+E286 -> 8
... A305: 46326 | B305: =UPPER(TEXT(A305,"DDD")) -> SÁB | C305: 0 | D305: =MONTH(A305) -> 10 | E305: =Tabela5[[#This Row],[DU]]+E304 -> 21
A306: 46327 | B306: =UPPER(TEXT(A306,"DDD")) -> DOM | C306: 0 | D306: =MONTH(A306) -> 11 | E306: =Tabela5[[#This Row],[DU]] -> 0
A307: 46328 | B307: =UPPER(TEXT(A307,"DDD")) -> SEG | C307: 0 | D307: =MONTH(A307) -> 11 | E307: =Tabela5[[#This Row],[DU]]+E306 -> 0
A308: 46329 | B308: =UPPER(TEXT(A308,"DDD")) -> TER | C308: 1 | D308: =MONTH(A308) -> 11 | E308: =Tabela5[[#This Row],[DU]]+E307 -> 1
A309: 46330 | B309: =UPPER(TEXT(A309,"DDD")) -> QUA | C309: 1 | D309: =MONTH(A309) -> 11 | E309: =Tabela5[[#This Row],[DU]]+E308 -> 2
A310: 46331 | B310: =UPPER(TEXT(A310,"DDD")) -> QUI | C310: 1 | D310: =MONTH(A310) -> 11 | E310: =Tabela5[[#This Row],[DU]]+E309 -> 3
A311: 46332 | B311: =UPPER(TEXT(A311,"DDD")) -> SEX | C311: 1 | D311: =MONTH(A311) -> 11 | E311: =Tabela5[[#This Row],[DU]]+E310 -> 4
A312: 46333 | B312: =UPPER(TEXT(A312,"DDD")) -> SÁB | C312: 0 | D312: =MONTH(A312) -> 11 | E312: =Tabela5[[#This Row],[DU]]+E311 -> 4
A313: 46334 | B313: =UPPER(TEXT(A313,"DDD")) -> DOM | C313: 0 | D313: =MONTH(A313) -> 11 | E313: =Tabela5[[#This Row],[DU]]+E312 -> 4
A314: 46335 | B314: =UPPER(TEXT(A314,"DDD")) -> SEG | C314: 1 | D314: =MONTH(A314) -> 11 | E314: =Tabela5[[#This Row],[DU]]+E313 -> 5
A315: 46336 | B315: =UPPER(TEXT(A315,"DDD")) -> TER | C315: 1 | D315: =MONTH(A315) -> 11 | E315: =Tabela5[[#This Row],[DU]]+E314 -> 6
A316: 46337 | B316: =UPPER(TEXT(A316,"DDD")) -> QUA | C316: 1 | D316: =MONTH(A316) -> 11 | E316: =Tabela5[[#This Row],[DU]]+E315 -> 7
A317: 46338 | B317: =UPPER(TEXT(A317,"DDD")) -> QUI | C317: 1 | D317: =MONTH(A317) -> 11 | E317: =Tabela5[[#This Row],[DU]]+E316 -> 8
A318: 46339 | B318: =UPPER(TEXT(A318,"DDD")) -> SEX | C318: 1 | D318: =MONTH(A318) -> 11 | E318: =Tabela5[[#This Row],[DU]]+E317 -> 9
... A335: 46356 | B335: =UPPER(TEXT(A335,"DDD")) -> SEG | C335: 1 | D335: =MONTH(A335) -> 11 | E335: =Tabela5[[#This Row],[DU]]+E334 -> 19
A336: 46357 | B336: =UPPER(TEXT(A336,"DDD")) -> TER | C336: 1 | D336: =MONTH(A336) -> 12 | E336: =Tabela5[[#This Row],[DU]] -> 1
A337: 46358 | B337: =UPPER(TEXT(A337,"DDD")) -> QUA | C337: 1 | D337: =MONTH(A337) -> 12 | E337: =Tabela5[[#This Row],[DU]]+E336 -> 2
A338: 46359 | B338: =UPPER(TEXT(A338,"DDD")) -> QUI | C338: 1 | D338: =MONTH(A338) -> 12 | E338: =Tabela5[[#This Row],[DU]]+E337 -> 3
A339: 46360 | B339: =UPPER(TEXT(A339,"DDD")) -> SEX | C339: 1 | D339: =MONTH(A339) -> 12 | E339: =Tabela5[[#This Row],[DU]]+E338 -> 4
A340: 46361 | B340: =UPPER(TEXT(A340,"DDD")) -> SÁB | C340: 0 | D340: =MONTH(A340) -> 12 | E340: =Tabela5[[#This Row],[DU]]+E339 -> 4
A341: 46362 | B341: =UPPER(TEXT(A341,"DDD")) -> DOM | C341: 0 | D341: =MONTH(A341) -> 12 | E341: =Tabela5[[#This Row],[DU]]+E340 -> 4
A342: 46363 | B342: =UPPER(TEXT(A342,"DDD")) -> SEG | C342: 1 | D342: =MONTH(A342) -> 12 | E342: =Tabela5[[#This Row],[DU]]+E341 -> 5
A343: 46364 | B343: =UPPER(TEXT(A343,"DDD")) -> TER | C343: 1 | D343: =MONTH(A343) -> 12 | E343: =Tabela5[[#This Row],[DU]]+E342 -> 6
A344: 46365 | B344: =UPPER(TEXT(A344,"DDD")) -> QUA | C344: 1 | D344: =MONTH(A344) -> 12 | E344: =Tabela5[[#This Row],[DU]]+E343 -> 7
A345: 46366 | B345: =UPPER(TEXT(A345,"DDD")) -> QUI | C345: 1 | D345: =MONTH(A345) -> 12 | E345: =Tabela5[[#This Row],[DU]]+E344 -> 8
A346: 46367 | B346: =UPPER(TEXT(A346,"DDD")) -> SEX | C346: 1 | D346: =MONTH(A346) -> 12 | E346: =Tabela5[[#This Row],[DU]]+E345 -> 9
A347: 46368 | B347: =UPPER(TEXT(A347,"DDD")) -> SÁB | C347: 0 | D347: =MONTH(A347) -> 12 | E347: =Tabela5[[#This Row],[DU]]+E346 -> 9
A348: 46369 | B348: =UPPER(TEXT(A348,"DDD")) -> DOM | C348: 0 | D348: =MONTH(A348) -> 12 | E348: =Tabela5[[#This Row],[DU]]+E347 -> 9
... A366: 46387 | B366: =UPPER(TEXT(A366,"DDD")) -> QUI | C366: 1 | D366: =MONTH(A366) -> 12 | E366: =Tabela5[[#This Row],[DU]]+E365 -> 22

Sheet Acomp_Modernização
A1: AT | B1: DATA CADASTRO | C1: DATA INICIO | D1: DATA FINAL | E1: Endereço | F1: Número | G1: TIPO | H1: STATUS | I1: Fibras | J1: MÊS | K1: SEMANA | L1: DIA
A2: VM | B2: 46126 | C2: 46135 | D2: 46136 | E2: Professora Carolina Ribeiro | F2: 165 | G2: MODERNIZAÇÃO | H2: SERVIÇO OK | I2: 8 | J2: 4 | K2: 17 | L2: 24
A3: JD | B3: 46134 | C3: 46148 | D3: 46150 | E3: Al Min Rocha de Azevedo | F3: 1388 | G3: MODERNIZAÇÃO | H3: SERVIÇO OK | I3: - | J3: 5 | K3: 19 | L3: 8
A4: VM | B4: 46153 | C4: 46161 | D4: 46162 | E4: DR Nicolau de Sousa Queiros | F4: 863 | G4: MODERNIZAÇÃO/ALÍVIO | H4: SERVIÇO OK | I4: - | J4: 5 | K4: 21 | L4: 20
A5: JD | B5: 46155 | C5: 46167 | D5: 46168 | E5: Francisco Leitão | F5: 486 | G5: MODERNIZAÇÃO/ALÍVIO | H5: SERVIÇO OK | I5: - | J5: 5 | K5: 22 | L5: 26
A6: JD | B6: 46155 | C6: 46169 | D6: 46171 | E6: Bela Cintra | F6: 1714 | G6: MODERNIZAÇÃO/ALÍVIO | H6: SERVIÇO OK | I6: - | J6: 5 | K6: 22 | L6: 29
A7: JD | B7: 46134 | C7: 46175 | D7: 46175 | E7: Rua Augusta | F7: 2445 | G7: MODERNIZAÇÃO | H7: SERVIÇO OK | I7: - | J7: 6 | K7: 23 | L7: 2
A8: PA | B8: 46130 | C8: 46181 | D8: 46182 | E8: Al. Ribeirão preto | F8: 111 | G8: MODERNIZAÇÃO | H8: SERVIÇO OK | I8: - | J8: 6 | K8: 24 | L8: 9
A9: JD | B9: 46155 | C9: 46183 | D9: 46183 | E9: Rua Arruda Alvim | F9: 36 | G9: MODERNIZAÇÃO/ALÍVIO | H9: SERVIÇO OK | I9: - | J9: 6 | K9: 24 | L9: 10
A10: HM | B10: 46142 | C10: 46188 | D10: 46191 | E10: Rua Leopoldo couto de magalhaes | F10: 1400 | G10: MODERNIZAÇÃO | H10: SERVIÇO OK | I10: - | J10: 6 | K10: 25 | L10: 18
A11: JD | B11: 46189 | C11: 46197 | D11: 46198 | E11: Rua Capote Valente | F11: 1181 | G11: MODERNIZAÇÃO/ALÍVIO | H11: SERVIÇO OK | I11: - | J11: 6 | K11: 26 | L11: 25
A12: PA | B12: 46183 | C12: 46198 | D12: 46198 | E12: Maestro Cardim | F12: 1273 | G12: MODERNIZAÇÃO | H12: SERVIÇO OK | I12: 4 | J12: 6 | K12: 26 | L12: 25
A13: VM | B13: 46198 | C13: 46202 | D13: 46202 | E13: Rua Dona Brígida | F13: 359 | G13: MODERNIZAÇÃO | H13: SERVIÇO OK | I13: 8 | J13: 6 | K13: 27 | L13: 29
A14: PA | B14: 46170 | C14: 46202 | D14: 46206 | E14: Av. Nove de julho | F14: 1967 | G14: MODERNIZAÇÃO | H14: SERVIÇO OK | I14: 56 | J14: 6 | K14: 27 | L14: 3
A15: HM | B15: 46203 | C15: 46209 | D15: 46209 | E15: Cojuba | F15: 136 | G15: MODERNIZAÇÃO | H15: SERVIÇO OK | I15: 16 | J15: 7 | K15: 28 | L15: 6
A16: PI | B16: 46192 | C16: 46209 | D16: 46210 | E16: Av Brigadeiro Faria Lima | F16: 2081 | G16: MODERNIZAÇÃO | H16: SERVIÇO OK | I16: 24 | J16: 7 | K16: 28 | L16: 7
A17: JD | B17: 46199 | C17: 46210 | D17: 46211 | E17: Rua da Consolação | F17: 3367 | G17: MODERNIZAÇÃO | H17: SERVIÇO OK | I17: 40 | J17: 7 | K17: 28 | L17: 8
A18: JD | B18: 46203 | C18: 46211 | D18: 46211 | E18: Oscar Freire | F18: 1961 | G18: MODERNIZAÇÃO | H18: SERVIÇO OK | I18: 32 | J18: 7 | K18: 28 | L18: 8
A19: JD | B19: 46205 | C19: 46216 | D19: 46217 | E19: Oscar Freire | F19: 1431 | G19: MODERNIZAÇÃO | H19: SERVIÇO OK | I19: 24 | J19: 7 | K19: 29 | L19: 14
A20: JD | B20: 46199 | C20: 46218 | D20: 46218 | E20: Rua Lisboa | F20: 159 | G20: MODERNIZAÇÃO | H20: SERVIÇO OK | I20: 8 | J20: 7 | K20: 29 | L20: 15
A21: VM | B21: 46205 | C21: 46218 | D21: 46220 | E21: Rua Carlos Petit | F21: 135 | G21: MODERNIZAÇÃO | H21: SERVIÇO OK | I21: 56 | J21: 7 | K21: 29 | L21: 17
A22: VM | B22: 46223 | C22: 46226 | D22: 46226 | E22: Av Prefeito Fábio Prado | F22: 655 | G22: MODERNIZAÇÃO | H22: SERVIÇO OK | I22: 8 | J22: 7 | K22: 30 | L22: 23
A23: IM | B23: 46230 | C23: 46230 | D23: 46231 | E23: Av. são Gabriel | F23: 339 | G23: MODERNIZAÇÃO | H23: SERVIÇO OK | I23: 16 | J23: 7 | K23: 31 | L23: 28
... A126: JD | B126: 46323 | C126: 46379 | D126: 46379 | E126: Rua Francisco Leitão | F126: 235 | G126: MODERNIZAÇÃO | H126: AGENDADO | I126: 16 | J126: 12 | K126: 52 | L126: 23

Sheet Modernização
A1: Data Final | B1: AT | C1: MÊS | D1: SEMANA | E1: STATUS
A2: 46136 | B2: VM | C2: =MONTH(A2) -> 4 | D2: =WEEKNUM(A2) -> 17 | E2: CONCLUÍDO
A3: 46150 | B3: JD | C3: =MONTH(A3) -> 5 | D3: =WEEKNUM(A3) -> 19 | E3: CONCLUÍDO
A4: 46162 | B4: VM | C4: =MONTH(A4) -> 5 | D4: =WEEKNUM(A4) -> 21 | E4: CONCLUÍDO
A5: 46168 | B5: JD | C5: =MONTH(A5) -> 5 | D5: =WEEKNUM(A5) -> 22 | E5: CONCLUÍDO
A6: 46171 | B6: JD | C6: =MONTH(A6) -> 5 | D6: =WEEKNUM(A6) -> 22 | E6: CONCLUÍDO
A7: 46175 | B7: JD | C7: =MONTH(A7) -> 6 | D7: =WEEKNUM(A7) -> 23 | E7: CONCLUÍDO
A8: 46181 | B8: PA | C8: =MONTH(A8) -> 6 | D8: =WEEKNUM(A8) -> 24 | E8: CONCLUÍDO
A9: 46183 | B9: JD | C9: =MONTH(A9) -> 6 | D9: =WEEKNUM(A9) -> 24 | E9: CONCLUÍDO
A10: 46188 | B10: HM | C10: =MONTH(A10) -> 6 | D10: =WEEKNUM(A10) -> 25 | E10: CONCLUÍDO
A11: 46197 | B11: JD | C11: =MONTH(A11) -> 6 | D11: =WEEKNUM(A11) -> 26 | E11: CONCLUÍDO
A12: 46198 | B12: PA | C12: =MONTH(A12) -> 6 | D12: =WEEKNUM(A12) -> 26 | E12: CONCLUÍDO
A13: 46202 | B13: VM | C13: =MONTH(A13) -> 6 | D13: =WEEKNUM(A13) -> 27 | E13: CONCLUÍDO
... A82: 46318 | B82: JD | C82: =MONTH(A82) -> 10 | D82: =WEEKNUM(A82) -> 43 | E82: CONCLUÍDO
